Workbook

Sheet Summary
A1: Real-source ingestion test (spec 0006), re-run after the spec 0007 fixes (A1) and with extractor v4 (A2, spec 0008)
A2: Satisfaction rule (fixed before results): Good = Hit@5 at least 90% and the run published; Acceptable = Hit@5 at least 75%; Poor = otherwise, or the run did not publish.
A4: Round | B4: What changed | C4: Source | D4: Answerable questions | E4: Hit@1 | F4: Hit@5 | G4: Hit@1 % | H4: Hit@5 % | I4: Run published | J4: Satisfaction
A5: R1 | B5: Recommended settings (v2) | C5: W1 | D5: =COUNTIFS(Retrieval!$A$2:$A$402,A5,Retrieval!$B$2:$B$402,C5,Retrieval!$I$2:$I$402,"<>n/a") | E5: =COUNTIFS(Retrieval!$A$2:$A$402,A5,Retrieval!$B$2:$B$402,C5,Retrieval!$I$2:$I$402,"yes") | F5: =COUNTIFS(Retrieval!$A$2:$A$402,A5,Retrieval!$B$2:$B$402,C5,Retrieval!$J$2:$J$402,"yes") | G5: =IF(D5=0,0,E5/D5) | H5: =IF(D5=0,0,F5/D5) | I5: =IF(COUNTIFS(Structure!$A:$A,A5,Structure!$C:$C,C5,Structure!$D:$D,"succeeded")>0,"yes","no") | J5: =IF(I5="no","Poor (not published)",IF(H5>=0.9,"Good",IF(H5>=0.75,"Acceptable","Poor")))
A6: R1 | B6: Recommended settings (v2) | C6: W2 | D6: =COUNTIFS(Retrieval!$A$2:$A$402,A6,Retrieval!$B$2:$B$402,C6,Retrieval!$I$2:$I$402,"<>n/a") | E6: =COUNTIFS(Retrieval!$A$2:$A$402,A6,Retrieval!$B$2:$B$402,C6,Retrieval!$I$2:$I$402,"yes") | F6: =COUNTIFS(Retrieval!$A$2:$A$402,A6,Retrieval!$B$2:$B$402,C6,Retrieval!$J$2:$J$402,"yes") | G6: =IF(D6=0,0,E6/D6) | H6: =IF(D6=0,0,F6/D6) | I6: =IF(COUNTIFS(Structure!$A:$A,A6,Structure!$C:$C,C6,Structure!$D:$D,"succeeded")>0,"yes","no") | J6: =IF(I6="no","Poor (not published)",IF(H6>=0.9,"Good",IF(H6>=0.75,"Acceptable","Poor")))
A7: R1 | B7: Recommended settings (v2) | C7: W3 | D7: =COUNTIFS(Retrieval!$A$2:$A$402,A7,Retrieval!$B$2:$B$402,C7,Retrieval!$I$2:$I$402,"<>n/a") | E7: =COUNTIFS(Retrieval!$A$2:$A$402,A7,Retrieval!$B$2:$B$402,C7,Retrieval!$I$2:$I$402,"yes") | F7: =COUNTIFS(Retrieval!$A$2:$A$402,A7,Retrieval!$B$2:$B$402,C7,Retrieval!$J$2:$J$402,"yes") | G7: =IF(D7=0,0,E7/D7) | H7: =IF(D7=0,0,F7/D7) | I7: =IF(COUNTIFS(Structure!$A:$A,A7,Structure!$C:$C,C7,Structure!$D:$D,"succeeded")>0,"yes","no") | J7: =IF(I7="no","Poor (not published)",IF(H7>=0.9,"Good",IF(H7>=0.75,"Acceptable","Poor")))
A8: R1 | B8: Recommended settings (v2) | C8: W4 | D8: =COUNTIFS(Retrieval!$A$2:$A$402,A8,Retrieval!$B$2:$B$402,C8,Retrieval!$I$2:$I$402,"<>n/a") | E8: =COUNTIFS(Retrieval!$A$2:$A$402,A8,Retrieval!$B$2:$B$402,C8,Retrieval!$I$2:$I$402,"yes") | F8: =COUNTIFS(Retrieval!$A$2:$A$402,A8,Retrieval!$B$2:$B$402,C8,Retrieval!$J$2:$J$402,"yes") | G8: =IF(D8=0,0,E8/D8) | H8: =IF(D8=0,0,F8/D8) | I8: =IF(COUNTIFS(Structure!$A:$A,A8,Structure!$C:$C,C8,Structure!$D:$D,"succeeded")>0,"yes","no") | J8: =IF(I8="no","Poor (not published)",IF(H8>=0.9,"Good",IF(H8>=0.75,"Acceptable","Poor")))
A9: R5 | B9: Publish the other pages and show warnings | C9: W1 | D9: =COUNTIFS(Retrieval!$A$2:$A$402,A9,Retrieval!$B$2:$B$402,C9,Retrieval!$I$2:$I$402,"<>n/a") | E9: =COUNTIFS(Retrieval!$A$2:$A$402,A9,Retrieval!$B$2:$B$402,C9,Retrieval!$I$2:$I$402,"yes") | F9: =COUNTIFS(Retrieval!$A$2:$A$402,A9,Retrieval!$B$2:$B$402,C9,Retrieval!$J$2:$J$402,"yes") | G9: =IF(D9=0,0,E9/D9) | H9: =IF(D9=0,0,F9/D9) | I9: =IF(COUNTIFS(Structure!$A:$A,A9,Structure!$C:$C,C9,Structure!$D:$D,"succeeded")>0,"yes","no") | J9: =IF(I9="no","Poor (not published)",IF(H9>=0.9,"Good",IF(H9>=0.75,"Acceptable","Poor")))
A10: R5 | B10: Publish the other pages and show warnings | C10: W2 | D10: =COUNTIFS(Retrieval!$A$2:$A$402,A10,Retrieval!$B$2:$B$402,C10,Retrieval!$I$2:$I$402,"<>n/a") | E10: =COUNTIFS(Retrieval!$A$2:$A$402,A10,Retrieval!$B$2:$B$402,C10,Retrieval!$I$2:$I$402,"yes") | F10: =COUNTIFS(Retrieval!$A$2:$A$402,A10,Retrieval!$B$2:$B$402,C10,Retrieval!$J$2:$J$402,"yes") | G10: =IF(D10=0,0,E10/D10) | H10: =IF(D10=0,0,F10/D10) | I10: =IF(COUNTIFS(Structure!$A:$A,A10,Structure!$C:$C,C10,Structure!$D:$D,"succeeded")>0,"yes","no") | J10: =IF(I10="no","Poor (not published)",IF(H10>=0.9,"Good",IF(H10>=0.75,"Acceptable","Poor")))
A11: R5 | B11: Publish the other pages and show warnings | C11: W3 | D11: =COUNTIFS(Retrieval!$A$2:$A$402,A11,Retrieval!$B$2:$B$402,C11,Retrieval!$I$2:$I$402,"<>n/a") | E11: =COUNTIFS(Retrieval!$A$2:$A$402,A11,Retrieval!$B$2:$B$402,C11,Retrieval!$I$2:$I$402,"yes") | F11: =COUNTIFS(Retrieval!$A$2:$A$402,A11,Retrieval!$B$2:$B$402,C11,Retrieval!$J$2:$J$402,"yes") | G11: =IF(D11=0,0,E11/D11) | H11: =IF(D11=0,0,F11/D11) | I11: =IF(COUNTIFS(Structure!$A:$A,A11,Structure!$C:$C,C11,Structure!$D:$D,"succeeded")>0,"yes","no") | J11: =IF(I11="no","Poor (not published)",IF(H11>=0.9,"Good",IF(H11>=0.75,"Acceptable","Poor")))
A12: R5 | B12: Publish the other pages and show warnings | C12: W4 | D12: =COUNTIFS(Retrieval!$A$2:$A$402,A12,Retrieval!$B$2:$B$402,C12,Retrieval!$I$2:$I$402,"<>n/a") | E12: =COUNTIFS(Retrieval!$A$2:$A$402,A12,Retrieval!$B$2:$B$402,C12,Retrieval!$I$2:$I$402,"yes") | F12: =COUNTIFS(Retrieval!$A$2:$A$402,A12,Retrieval!$B$2:$B$402,C12,Retrieval!$J$2:$J$402,"yes") | G12: =IF(D12=0,0,E12/D12) | H12: =IF(D12=0,0,F12/D12) | I12: =IF(COUNTIFS(Structure!$A:$A,A12,Structure!$C:$C,C12,Structure!$D:$D,"succeeded")>0,"yes","no") | J12: =IF(I12="no","Poor (not published)",IF(H12>=0.9,"Good",IF(H12>=0.75,"Acceptable","Poor")))
A13: R6 | B13: Chunks 300/400/40 | C13: W1 | D13: =COUNTIFS(Retrieval!$A$2:$A$402,A13,Retrieval!$B$2:$B$402,C13,Retrieval!$I$2:$I$402,"<>n/a") | E13: =COUNTIFS(Retrieval!$A$2:$A$402,A13,Retrieval!$B$2:$B$402,C13,Retrieval!$I$2:$I$402,"yes") | F13: =COUNTIFS(Retrieval!$A$2:$A$402,A13,Retrieval!$B$2:$B$402,C13,Retrieval!$J$2:$J$402,"yes") | G13: =IF(D13=0,0,E13/D13) | H13: =IF(D13=0,0,F13/D13) | I13: =IF(COUNTIFS(Structure!$A:$A,A13,Structure!$C:$C,C13,Structure!$D:$D,"succeeded")>0,"yes","no") | J13: =IF(I13="no","Poor (not published)",IF(H13>=0.9,"Good",IF(H13>=0.75,"Acceptable","Poor")))
A14: R6 | B14: Chunks 300/400/40 | C14: W2 | D14: =COUNTIFS(Retrieval!$A$2:$A$402,A14,Retrieval!$B$2:$B$402,C14,Retrieval!$I$2:$I$402,"<>n/a") | E14: =COUNTIFS(Retrieval!$A$2:$A$402,A14,Retrieval!$B$2:$B$402,C14,Retrieval!$I$2:$I$402,"yes") | F14: =COUNTIFS(Retrieval!$A$2:$A$402,A14,Retrieval!$B$2:$B$402,C14,Retrieval!$J$2:$J$402,"yes") | G14: =IF(D14=0,0,E14/D14) | H14: =IF(D14=0,0,F14/D14) | I14: =IF(COUNTIFS(Structure!$A:$A,A14,Structure!$C:$C,C14,Structure!$D:$D,"succeeded")>0,"yes","no") | J14: =IF(I14="no","Poor (not published)",IF(H14>=0.9,"Good",IF(H14>=0.75,"Acceptable","Poor")))
A15: R6 | B15: Chunks 300/400/40 | C15: W3 | D15: =COUNTIFS(Retrieval!$A$2:$A$402,A15,Retrieval!$B$2:$B$402,C15,Retrieval!$I$2:$I$402,"<>n/a") | E15: =COUNTIFS(Retrieval!$A$2:$A$402,A15,Retrieval!$B$2:$B$402,C15,Retrieval!$I$2:$I$402,"yes") | F15: =COUNTIFS(Retrieval!$A$2:$A$402,A15,Retrieval!$B$2:$B$402,C15,Retrieval!$J$2:$J$402,"yes") | G15: =IF(D15=0,0,E15/D15) | H15: =IF(D15=0,0,F15/D15) | I15: =IF(COUNTIFS(Structure!$A:$A,A15,Structure!$C:$C,C15,Structure!$D:$D,"succeeded")>0,"yes","no") | J15: =IF(I15="no","Poor (not published)",IF(H15>=0.9,"Good",IF(H15>=0.75,"Acceptable","Poor")))
A16: R6 | B16: Chunks 300/400/40 | C16: W4 | D16: =COUNTIFS(Retrieval!$A$2:$A$402,A16,Retrieval!$B$2:$B$402,C16,Retrieval!$I$2:$I$402,"<>n/a") | E16: =COUNTIFS(Retrieval!$A$2:$A$402,A16,Retrieval!$B$2:$B$402,C16,Retrieval!$I$2:$I$402,"yes") | F16: =COUNTIFS(Retrieval!$A$2:$A$402,A16,Retrieval!$B$2:$B$402,C16,Retrieval!$J$2:$J$402,"yes") | G16: =IF(D16=0,0,E16/D16) | H16: =IF(D16=0,0,F16/D16) | I16: =IF(COUNTIFS(Structure!$A:$A,A16,Structure!$C:$C,C16,Structure!$D:$D,"succeeded")>0,"yes","no") | J16: =IF(I16="no","Poor (not published)",IF(H16>=0.9,"Good",IF(H16>=0.75,"Acceptable","Poor")))
... A66: A3 | B66: Extract v5: recommended | C66: G8 | D66: =COUNTIFS(Retrieval!$A$2:$A$402,A66,Retrieval!$B$2:$B$402,C66,Retrieval!$I$2:$I$402,"<>n/a") | E66: =COUNTIFS(Retrieval!$A$2:$A$402,A66,Retrieval!$B$2:$B$402,C66,Retrieval!$I$2:$I$402,"yes") | F66: =COUNTIFS(Retrieval!$A$2:$A$402,A66,Retrieval!$B$2:$B$402,C66,Retrieval!$J$2:$J$402,"yes") | G66: =IF(D66=0,0,E66/D66) | H66: =IF(D66=0,0,F66/D66) | I66: =IF(COUNTIFS(Structure!$A:$A,A66,Structure!$C:$C,C66,Structure!$D:$D,"succeeded")>0,"yes","no") | J66: =IF(I66="no","Poor (not published)",IF(H66>=0.9,"Good",IF(H66>=0.75,"Acceptable","Poor")))
A68: Total embedding estimate (USD) | D68: =Runs!S20
A69: Total answer cost (USD) | D69: =Answers!K120
A70: Total spend (USD, embedding upper bound + recorded answers) | D70: =D68+D69
A71: Spending cap (USD) | D71: 1
A73: Recommendation
A74: Keep visible: If a file can't be read well, Languages in scanned pages, Chunk size (target / maximum / overlap).
A75: Keep in Advanced: Extractor version (v1 / v2), Maximum OCR pages, Quality thresholds (empty pages, characters, OCR confidence, reading order, malformed tables), Language policy (allowlist, confidence, mixed languages).
A76: Candidate to remove: Read scanned pages (OCR), OCR resolution (DPI), Per-page OCR timeout, Detect rotation / deskew, Extraction strategy (Auto / Native / Layout-aware), Table evidence (Structured + Markdown / Markdown / Plain text).
A77: Fix first: X1 The recommended setting ('Stop and let me review') blocks an ordinary government report. | X2 Borderless PDF tables lose their rows: whole columns are merged into one cell, and cells over 1,000 characters are cut. | X3 'Publish the other files and show warnings' does not publish the others when a file cannot be read.

Sheet Sources
A1: ID | B1: Type | C1: Name | D1: URL(s) | E1: Licence | F1: Scope | G1: Fetched on | H1: SHA-256 (files)
A2: W1 | B2: Website | C2: Python tutorial | D2: https://docs.python.org/3/tutorial/ | E2: PSF documentation licence (PSF License Agreement) | F2: Crawl from https://docs.python.org/3/tutorial/, depth 1, at most 20 pages | G2: 2026-10-09
A3: W2 | B3: Website | C3: Wikipedia articles | D3: https://en.wikipedia.org/wiki/Solar_System https://en.wikipedia.org/wiki/Moon https://en.wikipedia.org/wiki/Mount_Everest https://en.wikipedia.org/wiki/Great_Barrier_Reef https://en.wikipedia.org/wiki/Amazon_River https://en.wikipedia.org/wiki/Photosynthesis https://en.wikipedia.org/wiki/Periodic_table https://en.wikipedia.org/wiki/Olympic_Games https://en.wikipedia.org/wiki/Euro https://en.wikipedia.org/wiki/Python_(programming_language) | E3: CC BY-SA 4.0 | F3: 10 listed URLs | G3: 2026-10-09
A4: W3 | B4: Website | C4: GOV.UK guidance | D4: https://www.gov.uk/national-minimum-wage-rates https://www.gov.uk/holiday-entitlement-rights https://www.gov.uk/maternity-pay-leave https://www.gov.uk/statutory-sick-pay https://www.gov.uk/redundancy-your-rights https://www.gov.uk/flexible-working https://www.gov.uk/calculate-your-redundancy-pay https://www.gov.uk/council-tax-bands https://www.gov.uk/vehicle-tax-rate-tables https://www.gov.uk/income-tax-rates | E4: Open Government Licence v3.0 | F4: 10 listed URLs | G4: 2026-10-09
A5: W4 | B5: Website | C5: MDN Web Docs | D5: https://developer.mozilla.org/en-US/docs/Web/HTTP/Reference/Status https://developer.mozilla.org/en-US/docs/Web/HTTP/Reference/Methods https://developer.mozilla.org/en-US/docs/Web/HTTP/Reference/Headers/Cache-Control https://developer.mozilla.org/en-US/docs/Web/JavaScript/Reference/Global_Objects/Array https://developer.mozilla.org/en-US/docs/Web/JavaScript/Guide/Closures https://developer.mozilla.org/en-US/docs/Web/CSS/Reference/Properties/display https://developer.mozilla.org/en-US/docs/Web/API/Fetch_API https://developer.mozilla.org/en-US/docs/Web/HTML/Reference/Elements/table https://developer.mozilla.org/en-US/docs/Web/CSS/Guides/Grid_layout https://developer.mozilla.org/en-US/docs/Web/HTTP/Guides/CORS | E5: CC BY-SA 2.5 | F5: 10 listed URLs | G5: 2026-10-09
A6: F1 | B6: File (PDF) | C6: BERT (NAACL 2019), two-column paper | D6: https://aclanthology.org/N19-1423.pdf | E6: CC BY 4.0 (ACL Anthology, papers from 2016 onward) | F6: 16 pages | G6: 2026-10-09 | H6: 987545ffb087f1ece898142c403a516baeabeb70ce19089397fac6f7db12c3d4
A7: F2 | B7: File (PDF) | C7: US Census Bureau P60-279, Income in the United States: 2022 | D7: https://www.census.gov/content/dam/Census/library/publications/2023/demo/p60-279.pdf | E7: Public domain (US federal government work) | F7: 62 pages | G7: 2026-10-09 | H7: ce921ae1c54b000b3c1defbe52762a5358b9b597a6cd01aee5b84671fab598c5
A8: F3 | B8: File (PDF) | C8: Surveyor VI mission report, JPL TR 32-1262 Part III, scanned pages 7-16 | D8: https://sic.lpl.arizona.edu/sites/sic.lpl.arizona.edu/files/surveyor/Surveyor_VI_NASA-TechnicalReport32-1262_Part-3.pdf | E8: NASA/JPL technical report, US government work; 10-page extract made locally without altering the scan images | F8: 10 pages | G8: 2026-10-09 | H8: e6b37144235757381364229a5c937246ec68727704564651401fba417a5da745
A9: F4 | B9: File (PDF) | C9: Eurostat, Chiffres clés sur l'Europe, édition 2019 (French) | D9: https://ec.europa.eu/eurostat/documents/3217494/10164473/KS-EI-19-001-FR_N.pdf/aef66e0b-f5fe-c4e1-67ac-3c3f01a44384 | E9: © European Union, 2019; reuse authorised with attribution (Commission Decision 2011/833/EU) | F9: 76 pages | G9: 2026-10-10 | H9: 9457b14c2fb44527eeb718ba7753bc5781d771db2b88447a723a42c65b5776af
A10: F5 | B10: File (PDF) | C10: USGS Circular 115, Estimated use of water in the United States, 1950 (1951 scan), image-only copy | D10: https://pubs.usgs.gov/circ/1951/0115/report.pdf | E10: Public domain (US federal government work) | F10: 16 pages | G10: 2026-10-10 | H10: 7c1d9fe14a6c7d7d065bfc3d018ef32fefc692ce36524dace01fd0908a181c23
A11: F6 | B11: File (DOCX) | C11: DfT, Local highways maintenance transparency report template (DOCX) | D11: https://assets.publishing.service.gov.uk/media/6a26d314f56856fd11c0b191/highways-maintenance-reports-template.docx | E11: Open Government Licence v3.0 | G11: 2026-10-10 | H11: eb468aeba7ed8ff0bac3382ddeaa8e56dc859bc9dc3d988d4389a1fe508dfc02
A12: F7 | B12: File (PPTX) | C12: Home Office/DfE, Designing and building a Prevent risk assessment (PPTX, 14 slides, 3 tables) | D12: https://assets.publishing.service.gov.uk/media/60a3d4a7d3bf7f28855b8ffd/Designing_and_building_a_Prevent_risk_assessment.pptx | E12: Open Government Licence v3.0 | F12: 14 pages | G12: 2026-10-10 | H12: 71e2e0fe0eacbb94867329cae876e1f119e8d2e7f76145cf289d12cb7873484f
A13: G1 | B13: File (PDF) | C13: IRS Form W-4 (2026), Employee's Withholding Certificate (form with worksheets and tables) | D13: https://www.irs.gov/pub/irs-pdf/fw4.pdf | E13: Public domain (US federal government work) | F13: 5 pages | G13: 2026-10-10 | H13: 92444d8856ce55d9e25dca8b6d1420634fc68b11e1ab1f760916ea29ddd312b2
A14: G2 | B14: File (PDF) | C14: NIST SP 800-63B, Digital Identity Guidelines: Authentication and Lifecycle Management (2017, updated 2020; withdrawn 2025 and kept for history) | D14: https://nvlpubs.nist.gov/nistpubs/SpecialPublications/NIST.SP.800-63b.pdf | E14: Public domain (US federal government work) | F14: 80 pages | G14: 2026-10-10 | H14: ccfce7510a1267933f912d023306c6e7d485f21be63d271108b61aad6139127e
A15: G3 | B15: File (PDF) | C15: GAO-23-900494, Fiscal Year 2024 Budget Request (testimony with charts and tables) | D15: https://www.gao.gov/assets/gao-23-900494.pdf | E15: Public domain (US federal government work; GAO notes third-party images may be copyrighted) | F15: 20 pages | G15: 2026-10-10 | H15: 7ae5716dd9fb8792c59eb1c4d623d33c13f505b914229b62b0932c151f6f8f88
A16: G4 | B16: File (PDF) | C16: Executive Order 9066 (1942), first page, typed scan, image-only copy | D16: https://www.archives.gov/files/milestone-documents/images/doc-074-big.jpg | E16: Public domain (US federal government record, National Archives) | F16: 1 pages | G16: 2026-10-10 | H16: 2c7e202d431a762814ccdde34ff7c04b1d1a154d6bb1e02f2ad67a1a687f9096
A17: G5 | B17: File (XLSX) | C17: NISRA, Labour Force Survey quarterly tables, October to December 2023 (XLSX, 27 sheets) | D17: https://www.nisra.gov.uk/system/files/statistics/lmr-labour-force-survey-quarterly-tables-october-december-2023.xlsx | E17: Open Government Licence v3.0 (NISRA) | G17: 2026-10-10 | H17: 29a67242b51a9efcd349da8d7d03bf05d3ca479b462374954db44d4e55b907de
A18: G6 | B18: File (PPTX) | C18: ECGD, organisation chart and pay data, September 2012 (PPTX, 3 slides) | D18: https://www.gov.uk/government/uploads/system/uploads/attachment_data/file/190924/ecgd-structure-chart-september-2012.pptx | E18: Open Government Licence (data.gov.uk record) | F18: 3 pages | G18: 2026-10-10 | H18: 1f1192e07415540cdd422d8cb1c0e4fd851af43cb5c63341e867cb7188dda596
A19: G7 | B19: File (DOCX) | C19: DfE, Information sharing agreement template for childminder agencies and local authorities (DOCX) | D19: https://assets.publishing.service.gov.uk/media/69a988838fd807b03bbe92d0/Information_sharing_agreement_template_for_childminder_agencies_and_local_authorities.docx | E19: Open Government Licence v3.0 | G19: 2026-10-10 | H19: 6bc63fd49da37883f35c007ab6ad9a5fdf6b5daf3bd0b0155b35e1c3d04b0a65
A20: G8 | B20: File (PDF) | C20: Pan et al. (2023), Sex difference in driving speed management, PLOS ONE 18(7): e0288653 | D20: https://journals.plos.org/plosone/article/file?id=10.1371/journal.pone.0288653&type=printable | E20: CC BY 4.0 | F20: 14 pages | G20: 2026-10-10 | H20: 0fe1665514be2c545374fd80ffac056d85dca33076960650515d52f68c4df886

Sheet Runs
A1: Round | B1: Track | C1: What changed | D1: Extractor | E1: OCR | F1: OCR DPI | G1: Max OCR pages | H1: Table evidence | I1: If a file can't be read well | J1: Chunk target / max / overlap | K1: Website pages | L1: Status | M1: Error | N1: Items ready | O1: Items failed | P1: Items excluded | Q1: Chunks | R1: Duration (s) | S1: Embedding cost est. (USD) | T1: Embedding tokens (app-reported) | U1: Embedding cost (app-reported, USD)
A2: R1 | B2: files | C2: Recommended settings (v2) | D2: layout-ocr-v2 | E2: auto | F2: 200 | G2: 50 | H2: preserve | I2: Stop and let me review | J2: 600 / 800 / 80 | K2: n/a | L2: failed | M2: One or more selected files could not be processed. Inspect run items and retry with a new run. | N2: 0 | O2: 1 | P2: 0 | Q2: 159 | R2: 0 | T2: not recorded | U2: not recorded
A3: R1 | B3: web | C3: Recommended settings (v2) | D3: n/a (HTML) | E3: n/a | F3: n/a | G3: n/a | H3: n/a (HTML) | I3: Stop and let me review | J3: 600 / 800 / 80 | K3: Fetched live | L3: succeeded | N3: 92 | O3: 0 | P3: 0 | Q3: 3209 | R3: 430 | S3: 0.040144 | T3: not recorded | U3: not recorded
A4: R1w | B4: files | C4: Recommended, publish others with warnings | D4: layout-ocr-v2 | E4: auto | F4: 200 | G4: 50 | H4: preserve | I4: Publish the other files and show warnings | J4: 600 / 800 / 80 | K4: n/a | L4: succeeded | N4: 3 | O4: 0 | P4: 0 | Q4: 718 | R4: 94 | S4: 0.009012 | T4: not recorded | U4: not recorded
A5: R2 | B5: files | C5: Extractor layout-ocr-v1 | D5: layout-ocr-v1 | E5: auto | F5: 200 | G5: 50 | H5: preserve | I5: Publish the other files and show warnings | J5: 600 / 800 / 80 | K5: n/a | L5: succeeded | N5: 3 | O5: 0 | P5: 0 | Q5: 758 | R5: 90 | S5: 0.006846 | T5: not recorded | U5: not recorded
A6: R3a | B6: files | C6: OCR 300 DPI, 100 pages | D6: layout-ocr-v2 | E6: auto | F6: 300 | G6: 100 | H6: preserve | I6: Publish the other files and show warnings | J6: 600 / 800 / 80 | K6: n/a | L6: succeeded | N6: 3 | O6: 0 | P6: 0 | Q6: 718 | R6: 42 | S6: 0.009012 | T6: not recorded | U6: not recorded
A7: R3b | B7: files | C7: OCR off | D7: layout-ocr-v2 | E7: off | F7: 200 | G7: 50 | H7: preserve | I7: Publish the other files and show warnings | J7: 600 / 800 / 80 | K7: n/a | L7: failed | M7: One or more selected files could not be processed. Inspect run items and retry with a new run. | N7: 0 | O7: 1 | P7: 0 | Q7: 159 | R7: 0 | T7: not recorded | U7: not recorded
A8: R4 | B8: files | C8: Table evidence plain text | D8: layout-ocr-v2 | E8: auto | F8: 200 | G8: 50 | H8: plain_text | I8: Publish the other files and show warnings | J8: 600 / 800 / 80 | K8: n/a | L8: succeeded | N8: 3 | O8: 0 | P8: 0 | Q8: 684 | R8: 60 | S8: 0.008456 | T8: not recorded | U8: not recorded
A9: R5 | B9: web | C9: Publish the other pages and show warnings | D9: n/a (HTML) | E9: n/a | F9: n/a | G9: n/a | H9: n/a (HTML) | I9: Publish the other files and show warnings | J9: 600 / 800 / 80 | K9: Reused R1 snapshot | L9: succeeded | N9: 47 | O9: 0 | P9: 0 | Q9: 3209 | R9: 81 | S9: 0.040144 | T9: not recorded | U9: not recorded
A10: R6 | B10: files | C10: Chunks 300/400/40 | D10: layout-ocr-v2 | E10: auto | F10: 200 | G10: 50 | H10: preserve | I10: Publish the other files and show warnings | J10: 300 / 400 / 40 | K10: n/a | L10: succeeded | N10: 3 | O10: 0 | P10: 0 | Q10: 1593 | R10: 222 | S10: 0.013111 | T10: not recorded | U10: not recorded
A11: R6 | B11: web | C11: Chunks 300/400/40 | D11: n/a (HTML) | E11: n/a | F11: n/a | G11: n/a | H11: n/a (HTML) | I11: Stop and let me review | J11: 300 / 400 / 40 | K11: Reused R1 snapshot | L11: succeeded | N11: 47 | O11: 0 | P11: 0 | Q11: 6198 | R11: 688 | S11: 0.043422 | T11: not recorded | U11: not recorded
A12: A1 | B12: files | C12: After fixes: recommended (v3) | D12: layout-ocr-v3 | E12: auto | F12: 200 | G12: 50 | H12: preserve | I12: Stop and let me review | J12: 600 / 800 / 80 | K12: n/a | L12: succeeded | N12: 3 | O12: 0 | P12: 0 | Q12: 698 | R12: 14 | S12: 0.008666 | T12: 0 | U12: 0
A13: A1 | B13: web | C13: After fixes: recommended (v3) | D13: n/a (HTML) | E13: n/a | F13: n/a | G13: n/a | H13: n/a (HTML) | I13: Publish the other files and show warnings | J13: 600 / 800 / 80 | K13: Reused R1 snapshot | L13: succeeded | N13: 47 | O13: 0 | P13: 0 | Q13: 2381 | R13: 237 | S13: 0.028906 | T13: 137559 | U13: 0.00275118
A14: A2 | B14: files | C14: Extract v4: recommended | D14: layout-ocr-v4 | E14: auto | F14: 200 | G14: 100 | H14: preserve | I14: Stop and let me review | J14: 600 / 800 / 80 | K14: n/a | L14: succeeded | N14: 3 | O14: 0 | P14: 0 | Q14: 637 | R14: 85 | S14: 0.007748 | T14: 57835 | U14: 0.0011567
A15: A2 | B15: new | C15: Extract v4: recommended | D15: layout-ocr-v4 | E15: auto | F15: 200 | G15: 100 | H15: preserve | I15: Publish the other files and show warnings | J15: 600 / 800 / 80 | K15: n/a | L15: succeeded | N15: 4 | O15: 0 | P15: 0 | Q15: 1030 | R15: 168 | S15: 0.005961 | T15: 94681 | U15: 0.00189362
A16: A3 | B16: d2 | C16: Extract v5: recommended | D16: layout-ocr-v5 | E16: auto | F16: 200 | G16: 100 | H16: preserve | I16: Publish the other files and show warnings | J16: 600 / 800 / 80 | K16: n/a | L16: succeeded | N16: 8 | O16: 0 | P16: 0 | Q16: 844 | R16: 155 | S16: 0.009523 | T16: 110195 | U16: 0.0022039
A17: A3 | B17: files | C17: Extract v5: recommended | D17: layout-ocr-v5 | E17: auto | F17: 200 | G17: 100 | H17: preserve | I17: Stop and let me review | J17: 600 / 800 / 80 | K17: n/a | L17: succeeded | N17: 3 | O17: 0 | P17: 0 | Q17: 707 | R17: 72 | S17: 0.009333 | T17: 87675 | U17: 0.0017535
A18: A3 | B18: new | C18: Extract v5: recommended | D18: layout-ocr-v5 | E18: auto | F18: 200 | G18: 100 | H18: preserve | I18: Stop and let me review | J18: 600 / 800 / 80 | K18: n/a | L18: succeeded | N18: 4 | O18: 0 | P18: 0 | Q18: 1025 | R18: 64 | S18: 0.004786 | T18: 7873 | U18: 0.00015746
A20: Total embedding estimate (USD) | S20: =SUM(S2:S18)
A21: Estimate basis: indexed UTF-8 bytes x $0.02 per million (OpenRouter list price for openai/text-embedding-3-small, 2026-10-09). Bytes overstate tokens, so this is an upper bound. From A1 (spec 0007) the app records the provider-reported usage; earlier runs show 'not recorded'.

Sheet Structure
A1: Round | B1: Track | C1: Source | D1: Run status | E1: Items | F1: Items ready | G1: Items failed | H1: Items excluded | I1: Pages or URLs indexed | J1: Chunks | K1: Median chunk tokens | L1: Max chunk tokens | M1: Chunks with section path (%) | N1: Table chunks (pipe rows) | O1: Table chunks with header | P1: Short single-line chunks
A2: R1 | B2: files | C2: F1 | D2: failed | E2: 1 | F2: 0 | G2: 0 | H2: 0 | I2: 0 | J2: 0 | N2: 0 | O2: 0 | P2: 0
A3: R1 | B3: files | C3: F2 | D3: failed | E3: 1 | F3: 0 | G3: 1 | H3: 0 | I3: 0 | J3: 0 | N3: 0 | O3: 0 | P3: 0
A4: R1 | B4: files | C4: F3 | D4: failed | E4: 1 | F4: 0 | G4: 0 | H4: 0 | I4: 0 | J4: 0 | N4: 0 | O4: 0 | P4: 0
A5: R1 | B5: web | C5: W1 | D5: succeeded | E5: 56 | F5: 56 | G5: 0 | H5: 0 | I5: 17 | J5: 465 | K5: 616 | L5: 800 | M5: 96.3 | N5: 0 | O5: 0 | P5: 8
A6: R1 | B6: web | C6: W2 | D6: succeeded | E6: 10 | F6: 10 | G6: 0 | H6: 0 | I6: 10 | J6: 2288 | K6: 632 | L6: 800 | M6: 100 | N6: 0 | O6: 0 | P6: 25
A7: R1 | B7: web | C7: W3 | D7: succeeded | E7: 10 | F7: 10 | G7: 0 | H7: 0 | I7: 10 | J7: 57 | K7: 290 | L7: 710 | M7: 70.2 | N7: 0 | O7: 0 | P7: 8
A8: R1 | B8: web | C8: W4 | D8: succeeded | E8: 10 | F8: 10 | G8: 0 | H8: 0 | I8: 10 | J8: 399 | K8: 542 | L8: 796 | M8: 97.7 | N8: 0 | O8: 0 | P8: 22
A9: R1w | B9: files | C9: F1 | D9: succeeded | E9: 1 | F9: 1 | G9: 0 | H9: 0 | I9: 16 | J9: 159 | K9: 575 | L9: 795 | M9: 100 | N9: 6 | O9: 6 | P9: 4
A10: R1w | B10: files | C10: F2 | D10: succeeded | E10: 1 | F10: 1 | G10: 0 | H10: 0 | I10: 62 | J10: 536 | K10: 644.5 | L10: 800 | M10: 99.8 | N10: 232 | O10: 232 | P10: 7
A11: R1w | B11: files | C11: F3 | D11: succeeded | E11: 1 | F11: 1 | G11: 0 | H11: 0 | I11: 9 | J11: 23 | K11: 543 | L11: 799 | M11: 0 | N11: 0 | O11: 0 | P11: 1
A12: R2 | B12: files | C12: F1 | D12: succeeded | E12: 1 | F12: 1 | G12: 0 | H12: 0 | I12: 16 | J12: 189 | K12: 390 | L12: 795 | M12: 31.7 | N12: 5 | O12: 5 | P12: 12
A13: R2 | B13: files | C13: F2 | D13: succeeded | E13: 1 | F13: 1 | G13: 0 | H13: 0 | I13: 62 | J13: 545 | K13: 533 | L13: 800 | M13: 27.5 | N13: 149 | O13: 149 | P13: 45
A14: R2 | B14: files | C14: F3 | D14: succeeded | E14: 1 | F14: 1 | G14: 0 | H14: 0 | I14: 9 | J14: 24 | K14: 622 | L14: 654 | M14: 0 | N14: 0 | O14: 0 | P14: 1
A15: R3a | B15: files | C15: F1 | D15: succeeded | E15: 1 | F15: 1 | G15: 0 | H15: 0 | I15: 16 | J15: 159 | K15: 575 | L15: 795 | M15: 100 | N15: 6 | O15: 6 | P15: 4
A16: R3a | B16: files | C16: F2 | D16: succeeded | E16: 1 | F16: 1 | G16: 0 | H16: 0 | I16: 62 | J16: 536 | K16: 644.5 | L16: 800 | M16: 99.8 | N16: 232 | O16: 232 | P16: 7
A17: R3a | B17: files | C17: F3 | D17: succeeded | E17: 1 | F17: 1 | G17: 0 | H17: 0 | I17: 9 | J17: 23 | K17: 543 | L17: 799 | M17: 0 | N17: 0 | O17: 0 | P17: 1
A18: R3b | B18: files | C18: F1 | D18: failed | E18: 1 | F18: 0 | G18: 0 | H18: 0 | I18: 0 | J18: 0 | N18: 0 | O18: 0 | P18: 0
A19: R3b | B19: files | C19: F2 | D19: failed | E19: 1 | F19: 0 | G19: 0 | H19: 0 | I19: 0 | J19: 0 | N19: 0 | O19: 0 | P19: 0
A20: R3b | B20: files | C20: F3 | D20: failed | E20: 1 | F20: 0 | G20: 1 | H20: 0 | I20: 0 | J20: 0 | N20: 0 | O20: 0 | P20: 0
A21: R4 | B21: files | C21: F1 | D21: succeeded | E21: 1 | F21: 1 | G21: 0 | H21: 0 | I21: 16 | J21: 156 | K21: 572.5 | L21: 795 | M21: 100 | N21: 0 | O21: 0 | P21: 4
A22: R4 | B22: files | C22: F2 | D22: succeeded | E22: 1 | F22: 1 | G22: 0 | H22: 0 | I22: 62 | J22: 505 | K22: 636 | L22: 800 | M22: 99.8 | N22: 0 | O22: 0 | P22: 8
A23: R4 | B23: files | C23: F3 | D23: succeeded | E23: 1 | F23: 1 | G23: 0 | H23: 0 | I23: 9 | J23: 23 | K23: 543 | L23: 799 | M23: 0 | N23: 0 | O23: 0 | P23: 1
A24: R5 | B24: web | C24: W1 | D24: succeeded | E24: 17 | F24: 17 | G24: 0 | H24: 0 | I24: 17 | J24: 465 | K24: 616 | L24: 800 | M24: 96.3 | N24: 0 | O24: 0 | P24: 8
A25: R5 | B25: web | C25: W2 | D25: succeeded | E25: 10 | F25: 10 | G25: 0 | H25: 0 | I25: 10 | J25: 2288 | K25: 632 | L25: 800 | M25: 100 | N25: 0 | O25: 0 | P25: 25
A26: R5 | B26: web | C26: W3 | D26: succeeded | E26: 10 | F26: 10 | G26: 0 | H26: 0 | I26: 10 | J26: 57 | K26: 290 | L26: 710 | M26: 70.2 | N26: 0 | O26: 0 | P26: 8
A27: R5 | B27: web | C27: W4 | D27: succeeded | E27: 10 | F27: 10 | G27: 0 | H27: 0 | I27: 10 | J27: 399 | K27: 542 | L27: 796 | M27: 97.7 | N27: 0 | O27: 0 | P27: 22
A28: R6 | B28: files | C28: F1 | D28: succeeded | E28: 1 | F28: 1 | G28: 0 | H28: 0 | I28: 16 | J28: 275 | K28: 302 | L28: 400 | M28: 100 | N28: 10 | O28: 10 | P28: 4
A29: R6 | B29: files | C29: F2 | D29: succeeded | E29: 1 | F29: 1 | G29: 0 | H29: 0 | I29: 62 | J29: 1276 | K29: 378 | L29: 400 | M29: 99.9 | N29: 755 | O29: 755 | P29: 15
A30: R6 | B30: files | C30: F3 | D30: succeeded | E30: 1 | F30: 1 | G30: 0 | H30: 0 | I30: 9 | J30: 42 | K30: 315.5 | L30: 397 | M30: 0 | N30: 0 | O30: 0 | P30: 2
A31: R6 | B31: web | C31: W1 | D31: succeeded | E31: 17 | F31: 17 | G31: 0 | H31: 0 | I31: 17 | J31: 898 | K31: 318 | L31: 400 | M31: 100 | N31: 0 | O31: 0 | P31: 38
A32: R6 | B32: web | C32: W2 | D32: succeeded | E32: 10 | F32: 10 | G32: 0 | H32: 0 | I32: 10 | J32: 4506 | K32: 317 | L32: 400 | M32: 100 | N32: 0 | O32: 0 | P32: 58
... A63: A3 | B63: new | C63: F7 | D63: succeeded | E63: 1 | F63: 1 | G63: 0 | H63: 0 | I63: 14 | J63: 15 | K63: 378 | L63: 785 | M63: 0 | N63: 2 | O63: 2 | P63: 5

Sheet Retrieval
A1: Round | B1: Source | C1: Question ID | D1: Question | E1: Kind | F1: Expected phrase(s) | G1: Index used (round) | H1: First hit rank | I1: Hit@1 | J1: Hit@5 | K1: Top result source | L1: Top result section | M1: Top result excerpt
A2: R1 | B2: W1 | C2: w1-q1 | D2: Which class does the Python tutorial recommend for implementing a queue? | E2: text | F2: collections.deque | G2: R1 | H2: 2 | I2: no | J2: yes | K2: https://docs.python.org/3/tutorial/datastructures.html | L2: 5. Data Structures ¶ > 5.1. More on Lists ¶ > 5.1.2. Using Lists as Queues ¶ | M2: e which was designed to have fast appends and pops from both ends. For example: >>> from collections import deque >>> queue = deque(["Eric", "John", "Michael"]) >>> queue.append("Terry") # Terry arrives >>> queue.append("Graham")
A3: R1 | B3: W1 | C3: w1-q2 | D3: In CPython 3.3, where is the compiled version of a module named spam.py cached? | E3: code | F3: spam.cpython-33.pyc | G3: R1 | H3: 1 | I3: yes | J3: yes | K3: https://docs.python.org/3/tutorial/modules.html | L3: 6. Modules ¶ > 6.1. More on Modules ¶ | M3: 6.1.3. “Compiled” Python files ¶ To speed up loading modules, Python caches the compiled version of each module in the __pycache__ directory under the name module.version.pyc, where the version encodes the format of the compiled file; it generally c
A4: R1 | B4: W1 | C4: w1-q3 | D4: What command does the tutorial use to create a virtual environment called tutorial-env? | E4: code | F4: python -m venv tutorial-env | G4: R1 | H4: 1 | I4: yes | J4: yes | K4: https://docs.python.org/3/tutorial/venv.html | L4: 12. Virtual Environments and Packages ¶ | M4: 12.2. Creating Virtual Environments ¶ The module used to create and manage virtual environments is called venv. venv will install the Python version from which the command was run (as reported by the --version option). For instance, executing the c
A5: R1 | B5: W1 | C5: w1-q4 | D5: When is the else clause of a for loop executed? | E5: text | F5: if no break occurred | G5: R1 | H5: 2 | I5: no | J5: yes | K5: https://docs.python.org/3/tutorial/controlflow.html | L5: 4. More Control Flow Tools ¶ > 4.5. else Clauses on Loops ¶ | M5: . Look closely: the else clause belongs to the for loop, not the if statement.) One way to think of the else clause is to imagine it paired with the if inside the loop. As the loop executes, it will run a sequence like if/if/if/else. The if is ins
A6: R1 | B6: W1 | C6: w1-q5 | D6: What does the pass statement do? | E6: text | F6: the pass statement does nothing | G6: R1 | H6: 1 | I6: yes | J6: yes | K6: https://docs.python.org/3/tutorial/controlflow.html | L6: 4. More Control Flow Tools ¶ | M6: 4.6. pass Statements ¶ The pass statement does nothing. It can be used when a statement is required syntactically but the program requires no action. For example: >>> while True: ... pass # Busy-wait for keyboard interrupt (Ctrl+C) ... This i
A7: R1 | B7: W1 | C7: w1-q6 | D7: What does the list index() method return? | E7: list | F7: zero-based index of the first occurrence | G7: R1 | H7: 3 | I7: no | J7: yes | K7: https://developer.mozilla.org/en-US/docs/Web/JavaScript/Reference/Global_Objects/Array | L7: Array > Description > Iterative methods | M7: Note the following: Not all methods do the i in this test. The find, findIndex, findLast, and findLastIndex methods do not, but other methods do. The length is memorized before the loop starts. This affects how insertions and deletions during itera
A8: R1 | B8: W1 | C8: w1-q7 | D8: What is the short name for formatted string literals? | E8: text | F8: also called f-strings | G8: R1 | H8: 2 | I8: no | J8: yes | K8: https://docs.python.org/3/tutorial/inputoutput.html | L8: 7. Input and Output ¶ > 7.1. Fancier Output Formatting ¶ > 7.1.1. Formatted String Literals ¶ | M8: a minimum number of characters wide. This is useful for making columns line up. >>> table = {'Sjoerd': 4127, 'Jack': 4098, 'Dcab': 7678} >>> for name, phone in table.items(): ... print(f'{name:10} ==> {phone:10d}') ... Sjoerd ==> 4127
A9: R1 | B9: W1 | C9: w1-q8 | D9: On what date will Python 4.0 be released according to the tutorial? | E9: unanswerable | F9: (not in source) | G9: R1 | I9: n/a | J9: n/a | K9: https://en.wikipedia.org/wiki/Python_(programming_language) | L9: Python (programming language) > References | M9: ↑ "Python Developer's Guide – Python Developer's Guide". devguide.python.org. Archived from the original on 9 November 2020. Retrieved 17 December 2019. ↑ Hughes, Owen (24 May 2021). "Programming languages: Why Python 4.0 might never arrive, accordi
A10: R1 | B10: W2 | C10: w2-q1 | D10: What is the elevation of Mount Everest in metres? | E10: table | F10: 8,848.86 m | G10: R1 | H10: 2 | I10: no | J10: yes | K10: https://en.wikipedia.org/wiki/Mount_Everest | L10: Mount Everest > Surveys | M10: 21st century On 9 October 2005, after several months of measurement and calculation, the Chinese Academy of Sciences and State Bureau of Surveying and Mapping announced the height of Everest as 8,844.43 m (29,017.16 ft) with accuracy of ±0.21 m (8.3
A11: R1 | B11: W2 | C11: w2-q2 | D11: How many individual reefs make up the Great Barrier Reef? | E11: text | F11: over 2,900 individual reefs | G11: R1 | I11: no | J11: no | K11: https://en.wikipedia.org/wiki/Great_Barrier_Reef | L11: Great Barrier Reef | M11: The reef is located in the Coral Sea, off the coast of Queensland, Australia. It is separated from the coast by a channel 160 kilometres (100 mi) wide in places and over 61 metres (200 ft) deep.[7] The Great Barrier Reef can be seen from outer sp
A12: R1 | B12: W2 | C12: w2-q3 | D12: What is the average discharge of the Amazon River? | E12: text | F12: 215,000 to 230,000 cubic meters per second | G12: R1 | H12: 2 | I12: no | J12: yes | K12: https://en.wikipedia.org/wiki/Amazon_River | L12: Amazon River > Discharge | M12: Average discharge at the estuary; Period from 2003 to 2015: 7,200 km3/a (230,000 m3/s)[80][81] Year (km3) (m3/s) Year (km3) (m3/s) 2003 6,470 205,000 2010 6,464 205,000 2004 6,747 214,000 2011 7,378 234,000 2005 6,522 207,000 20
A13: R1 | B13: W2 | C13: w2-q4 | D13: When was the euro introduced to world financial markets as an accounting currency? | E13: text | F13: 1 january 1999 | G13: R1 | H13: 1 | I13: yes | J13: yes | K13: https://en.wikipedia.org/wiki/Euro | L13: Euro | M13: hest combined values of banknotes and coins in circulation in the world.[15][16] The name euro was officially adopted on 16 December 1995 in Madrid.[17] The euro was introduced to world financial markets as an accounting currency on 1 January 1999,
A14: R1 | B14: W2 | C14: w2-q5 | D14: Who published the first generally accepted periodic table, and in what year? | E14: text | F14: dmitri mendeleev in 1869 | G14: R1 | H14: 1 | I14: yes | J14: yes | K14: https://en.wikipedia.org/wiki/Periodic_table | L14: Periodic table | M14: The first periodic table to become generally accepted was that of the Russian chemist Dmitri Mendeleev in 1869; he formulated the periodic law as a dependence of chemical properties on atomic mass. As not all elements were then known, there were gaps
A15: R1 | B15: W2 | C15: w2-q6 | D15: What is the Moon's average distance from Earth? | E15: text | F15: 378,000 kilometers | G15: R1 | I15: no | J15: no | K15: https://en.wikipedia.org/wiki/Moon | L15: Moon > Explanatory notes | M15: ↑ The mean distance of the Moon from the Earth is 384401 {\displaystyle 384401} km. The equatorial radius of Earth is 6.378136 ⋅ 10
A16: R1 | B16: W2 | C16: w2-q7 | D16: When was Python 3.0 released? | E16: text | F16: python 3.0, released in 2008 | G16: R1 | H16: 2 | I16: no | J16: yes | K16: https://en.wikipedia.org/wiki/Python_(programming_language) | L16: Python (programming language) > History | M16: 12), with the plus signifying (at least some) "backported security updates".[56] Python 3.0 was released on 3 December 2008, and was a major revision and not completely backward-compatible with earlier versions, with some new semantics and changed s
A17: R1 | B17: W2 | C17: w2-q8 | D17: Who won the men's downhill at the 2030 Winter Olympics? | E17: unanswerable | F17: (not in source) | G17: R1 | I17: n/a | J17: n/a | K17: https://en.wikipedia.org/wiki/Olympic_Games | L17: Olympic Games > References | M17: ↑ Mather, Victor (21 February 2018). "Desperately Seeking Skiers for a Budding Olympic Sport". The New York Times. Archived from the original on 11 March 2018. Retrieved 24 June 2018. ↑ "Men to compete in artistic swimming at Olympics for first time
A18: R1 | B18: W3 | C18: w3-q1 | D18: What was the minimum hourly wage for workers under 18 from April 2024 to March 2025? | E18: table | F18: £6.40 | G18: R1 | H18: 1 | I18: yes | J18: yes | K18: https://www.gov.uk/national-minimum-wage-rates | L18: National Minimum Wage and National Living Wage rates > Previous rates | M18: Rates between 1 April 2024 and 31 March 2026 Since 1 April 2024 the National Living Wage has been for those aged 21 and over. 21 and over 18 to 20 Under 18 Apprentice April 2025 to March 2026 £12.21 £10 £7.55 £7.55 April 2024 to March 2025
A19: R1 | B19: W3 | C19: w3-q2 | D19: Which taxable income band does the 40% higher rate of Income Tax cover? | E19: table | F19: £50,271 to £125,140 | G19: R1 | H19: 1 | I19: yes | J19: yes | K19: https://www.gov.uk/income-tax-rates | L19: Current rates and allowances | M19: Income Tax rates and bands The table shows the tax rates you pay in each band if you have a standard Personal Allowance of £12,570. Income tax bands are different if you live in Scotland. Band Taxable income Tax rate Personal Allowance Up to £
A20: R1 | B20: W3 | C20: w3-q3 | D20: How much Statutory Sick Pay can you get per week? | E20: text | F20: £123.25 | G20: R1 | H20: 1 | I20: yes | J20: yes | K20: https://www.gov.uk/statutory-sick-pay | M20: Overview You can get up to £123.25 per week Statutory Sick Pay (SSP) if you’re too ill to work. It’s paid by your employer for up to 28 weeks. This guide is also available in Welsh (Cymraeg). You cannot get less than the statutory amount. You can
A21: R1 | B21: W3 | C21: w3-q4 | D21: How many days of paid annual leave must a worker on a 5-day week receive? | E21: text | F21: at least 28 days | G21: R1 | H21: 1 | I21: yes | J21: yes | K21: https://www.gov.uk/holiday-entitlement-rights | L21: Entitlement | M21: Statutory annual leave entitlement Most workers who work a 5-day week must receive at least 28 days’ paid annual leave a year. This is the equivalent of 5.6 weeks of holiday.
A22: R1 | B22: W3 | C22: w3-q5 | D22: How long must you have worked for your employer to qualify for statutory redundancy pay? | E22: text | F22: at least 2 years | G22: R1 | H22: 1 | I22: yes | J22: yes | K22: https://www.gov.uk/calculate-your-redundancy-pay | M22: Calculate your statutory redundancy pay Calculate how much statutory redundancy you can get. It’s based on age, weekly pay and number of years in the job. Your weekly pay is the average you earned per week over the 12 weeks before the day you got y
A23: R1 | B23: W3 | C23: w3-q6 | D23: What is the first vehicle tax payment for a petrol car emitting 111 to 130g/km of CO2? | E23: table | F23: 111 to 130g/km + £455 | G23: R1 | H23: 2 | I23: no | J23: yes | K23: https://www.gov.uk/vehicle-tax-rate-tables | L23: Cars registered on or after 1 April 2017 | M23: First tax payment when you register the vehicle You’ll pay a rate based on a vehicle’s CO2 emissions the first time it’s registered. This also applies to some motorhomes. You have to pay a higher rate for diesel cars that do not meet the Real Driv
A24: R1 | B24: W3 | C24: w3-q7 | D24: From when can an employee make a request for flexible working? | E24: text | F24: from their first day in a job | G24: R1 | H24: 1 | I24: yes | J24: yes | K24: https://www.gov.uk/flexible-working | M24: Overview Flexible working is a way of working that suits an employee’s needs, for example having flexible start and finish times, or working from home. Flexible working rules are different in Northern Ireland. All employees have the legal right to
A25: R1 | B25: W3 | C25: w3-q8 | D25: What is the weekly rate of Statutory Paternity Pay? | E25: unanswerable | F25: (not in source) | G25: R1 | I25: n/a | J25: n/a | K25: https://www.gov.uk/statutory-sick-pay | M25: Statutory Sick Pay (SSP)
A26: R1 | B26: W4 | C26: w4-q1 | D26: What does HTTP status 418 I'm a teapot mean? | E26: list | F26: brew coffee with a teapot | G26: R1 | H26: 1 | I26: yes | J26: yes | K26: https://developer.mozilla.org/en-US/docs/Web/HTTP/Reference/Status | L26: HTTP response status codes > Client error responses | M26: ted data is not supported by the server, so the server is rejecting the request. 416 Range Not Satisfiable The ranges specified by the Range header field in the request cannot be fulfilled. It's possible that the range is outside the size of the ta
A27: R1 | B27: W4 | C27: w4-q2 | D27: What does HTTP status 429 mean? | E27: list | F27: too many requests in a given amount of time | G27: R1 | H27: 1 | I27: yes | J27: yes | K27: https://developer.mozilla.org/en-US/docs/Web/HTTP/Reference/Status | L27: HTTP response status codes > Client error responses | M27: sends an Upgrade header in a 426 response to indicate the required protocol(s). 428 Precondition Required The origin server requires the request to be conditional. This response is intended to prevent the 'lost update' problem, where a client GETs
A28: R1 | B28: W4 | C28: w4-q3 | D28: How must multiple Cache-Control directives be separated? | E28: text | F28: must be comma-separated | G28: R1 | H28: 1 | I28: yes | J28: yes | K28: https://developer.mozilla.org/en-US/docs/Web/HTTP/Reference/Headers/Cache-Control | L28: Cache-Control header | M28: Syntax Cache-Control: <directive>, <directive>, ... Cache directives follow these rules: Caching directives are case-insensitive. However, lowercase is recommended because some implementations do not recognize uppercase directives. Multiple direc
A29: R1 | B29: W4 | C29: w4-q4 | D29: What is a closure in JavaScript? | E29: text | F29: combination of a function bundled together | G29: R1 | H29: 1 | I29: yes | J29: yes | K29: https://developer.mozilla.org/en-US/docs/Web/JavaScript/Guide/Closures | M29: Closures A closure is the combination of a function bundled together (enclosed) with references to its surrounding state (the lexical environment). In other words, a closure gives a function access to its outer scope. In JavaScript, closures are cre
A30: R1 | B30: W4 | C30: w4-q5 | D30: How many mandatory arguments does the fetch() method take? | E30: text | F30: one mandatory argument | G30: R1 | H30: 2 | I30: no | J30: yes | K30: https://developer.mozilla.org/en-US/docs/Web/API/Fetch_API | L30: Fetch API > Specifications | M30: Fetch# fetch-method Fetch# deferred-fetch
A31: R1 | B31: W4 | C31: w4-q6 | D31: What does the HTTP QUERY method do? | E31: text | F31: the query method initiates a server-side query | G31: R1 | H31: 2 | I31: no | J31: yes | K31: https://developer.mozilla.org/en-US/docs/Web/HTTP/Reference/Methods | M31: HTTP request methods HTTP defines a set of request methods to indicate the purpose of the request and what is expected if the request is successful. Although they can also be nouns, these request methods are sometimes referred to as HTTP verbs. Each
A32: R1 | B32: W4 | C32: w4-q7 | D32: In MDN's CORS preflight example, what value is sent in the Access-Control-Max-Age header? | E32: code | F32: access-control-max-age: 86400 | G32: R1 | I32: no | J32: no | K32: https://developer.mozilla.org/en-US/docs/Web/HTTP/Guides/CORS | L32: Cross-Origin Resource Sharing (CORS) > The HTTP response headers | M32: Access-Control-Max-Age The Access-Control-Max-Age header indicates how long the results of a preflight request can be cached. For an example of a preflight request, see the above examples. Access-Control-Max-Age: <delta-seconds> The delta-seconds
A33: R1 | B33: W4 | C33: w4-q8 | D33: Which HTTP status code means Payment Accepted? | E33: unanswerable | F33: (not in source) | G33: R1 | I33: n/a | J33: n/a | K33: https://developer.mozilla.org/en-US/docs/Web/HTTP/Reference/Status | L33: HTTP response status codes > Successful responses | M33: . This is typically the response sent after POST requests, or some PUT requests. 202 Accepted The request has been received but not yet acted upon. It is noncommittal, since there is no way in HTTP to later send an asynchronous response indicating
A34: R1 | B34: F1 | C34: f1-q1 | D34: What are the layer, hidden size and attention head settings of BERT-base? | E34: text | F34: l=12, h=768, a=12 | G34: no index | I34: no | J34: no
A35: R1 | B35: F1 | C35: f1-q2 | D35: What percentage of WordPiece tokens does BERT mask during pre-training? | E35: text | F35: 15% of all wordpiece | G35: no index | I35: no | J35: no
A36: R1 | B36: F1 | C36: f1-q3 | D36: What GLUE score did BERT reach? | E36: text | F36: glue score to 80.5% | G36: no index | I36: no | J36: no
A37: R1 | B37: F1 | C37: f1-q4 | D37: Which corpora were used to pre-train BERT? | E37: text | F37: bookscorpus (800m words) | G37: no index | I37: no | J37: no
A38: R1 | B38: F1 | C38: f1-q5 | D38: What SQuAD v1.1 Test F1 did BERT achieve? | E38: text | F38: 93.2 | G38: no index | I38: no | J38: no
A39: R1 | B39: F1 | C39: f1-q6 | D39: How many total parameters does BERT-large have? | E39: text | F39: total parameters=340m | G39: no index | I39: no | J39: no
A40: R1 | B40: F1 | C40: f1-q7 | D40: How many GPUs were used to train GPT-4? | E40: unanswerable | F40: (not in source) | G40: no index | I40: n/a | J40: n/a
A41: R1 | B41: F2 | C41: f2-q1 | D41: What was real median household income in the United States in 2022? | E41: text | F41: $74,580 | G41: no index | I41: no | J41: no
A42: R1 | B42: F2 | C42: f2-q2 | D42: By how much did real median household income change between 2021 and 2022? | E42: text | F42: 2.3 percent | G42: no index | I42: no | J42: no
A43: R1 | B43: F2 | C43: f2-q3 | D43: How did the money income Gini index change between 2021 and 2022? | E43: text | F43: from 0.494 to 0.488 | G43: no index | I43: no | J43: no
A44: R1 | B44: F2 | C44: f2-q4 | D44: What was the median income of married-couple households in 2022 according to Table A-1? | E44: table | F44: married-couple + 110,800 | G44: no index | I44: no | J44: no
A45: R1 | B45: F2 | C45: f2-q5 | D45: What was the median income of family households in 2022 according to Table A-1? | E45: table | F45: family households + 95,450 | G45: no index | I45: no | J45: no
... A55: R1 | B55: F3 | C55: f3-q8 | D55: What was the landing site latitude of Surveyor VII? | E55: unanswerable | F55: (not in source) | G55: no index | I55: n/a | J55: n/a
A56: R1w | B56: F1 | C56: f1-q1 | D56: What are the layer, hidden size and attention head settings of BERT-base? | E56: text | F56: l=12, h=768, a=12 | G56: R1w | H56: 2 | I56: no | J56: yes | K56: acl-n19-1423-bert.pdf | L56: Language Understanding > 5 Ablation Studies > 5.3 Feature-based Approach with BERT | M56: .99 84.4 86.7 92.9 12 1024 16 3.54 85.7 86.9 93.3 24 1024 16 3.23 86.6 87.8 93.7 Table 6: Ablation over BERT model size. #L = the number of layers; #H = hidden size; #A = number of attention heads. “LM (ppl)” is the masked LM perplexity of held-out
A57: R1w | B57: F1 | C57: f1-q2 | D57: What percentage of WordPiece tokens does BERT mask during pre-training? | E57: text | F57: 15% of all wordpiece | G57: R1w | H57: 2 | I57: no | J57: yes | K57: acl-n19-1423-bert.pdf | L57: Language Understanding > 3 BERT > 3.1 Pre-training BERT | M57: ), we only predict the masked words rather than reconstructing the entire input. Although this allows us to obtain a bidirectional pre-trained model, a downside is that we are creating a mismatch between pre-training and ﬁne-tuning, since the [MASK]
A58: R1w | B58: F1 | C58: f1-q3 | D58: What GLUE score did BERT reach? | E58: text | F58: glue score to 80.5% | G58: R1w | H58: 5 | I58: no | J58: yes | K58: acl-n19-1423-bert.pdf | L58: Language Understanding > 4 Experiments > 4.1 GLUE | M58: 85.8 88.9 66.4 79.6 BERTLARGE 86.7/85.9 72.1 92.7 94.9 60.5 86.5 89.3 70.1 82.1 Table 1: GLUE Test results, scored by the evaluation server (https://gluebenchmark.com/leaderboard). The number below each task denotes the number of training examples.
A59: R1w | B59: F1 | C59: f1-q4 | D59: Which corpora were used to pre-train BERT? | E59: text | F59: bookscorpus (800m words) | G59: R1w | H59: 1 | I59: yes | J59: yes | K59: acl-n19-1423-bert.pdf | L59: Language Understanding > 3 BERT > 3.1 Pre-training BERT | M59: ks, where BERT transfers all parameters to initialize end-task model parameters. Pre-training data The pre-training procedure largely follows the existing literature on language model pre-training. For the pre-training corpus we use the BooksCorpus
A60: R1w | B60: F1 | C60: f1-q5 | D60: What SQuAD v1.1 Test F1 did BERT achieve? | E60: text | F60: 93.2 | G60: R1w | H60: 2 | I60: no | J60: yes | K60: acl-n19-1423-bert.pdf | L60: Language Understanding > 4 Experiments > 4.2 SQuAD v1.1 | M60: rst ﬁne-tuning on TriviaQA (Joshi et al., 2017) befor ﬁne-tuning on SQuAD. Our best performing system outperforms the top leaderboard system by +1.5 F1 in ensembling and +1.3 F1 as a single system. In fact, our single BERT model outperforms the top
A61: R1w | B61: F1 | C61: f1-q6 | D61: How many total parameters does BERT-large have? | E61: text | F61: total parameters=340m | G61: R1w | H61: 2 | I61: no | J61: yes | K61: acl-n19-1423-bert.pdf | L61: Language Understanding > 5 Ablation Studies > 5.2 Effect of Model Size | M61: e literature is (L=64, H=512, A=2) with 235M parameters (Al-Rfou et al., 2018). By contrast, BERTBASE contains 110M parameters and BERTLARGE contains 340M parameters. It has long been known that increasing the model size will lead to continual imp
A62: R1w | B62: F1 | C62: f1-q7 | D62: How many GPUs were used to train GPT-4? | E62: unanswerable | F62: (not in source) | G62: R1w | I62: n/a | J62: n/a | K62: acl-n19-1423-bert.pdf | L62: Language Understanding > 5 Ablation Studies > 5.2 Effect of Model Size | M62: Results on selected GLUE tasks are shown in Table 6. In this table, we report the average Dev Set accuracy from 5 random restarts of ﬁne-tuning. We can see that larger models lead to a strict accuracy improvement across all four datasets, even for MR
A63: R1w | B63: F2 | C63: f2-q1 | D63: What was real median household income in the United States in 2022? | E63: text | F63: $74,580 | G63: R1w | H63: 1 | I63: yes | J63: yes | K63: census-p60-279.pdf | L63: Income in the United States: 2022 > HOUSEHOLD INCOME BY SELECTED CHARACTERISTICS > All Households | M63: All Households Real median household income was $74,580 in 2022, 2.3 percent lower than the 2021 estimate of $76,330. It was 4.7 percent lower than the 2019 median, the year before the start of the COVID-19 pandemic and the corresponding rece
A64: R1w | B64: F2 | C64: f2-q2 | D64: By how much did real median household income change between 2021 and 2022? | E64: text | F64: 2.3 percent | G64: R1w | H64: 2 | I64: no | J64: yes | K64: census-p60-279.pdf | L64: Income in the United States: 2022 > HOUSEHOLD INCOME BY SELECTED CHARACTERISTICS > Change: 2021 to 2022 2022 Median Income | M64: Change: 2021 to 2022 2022 Median Income
A65: R1w | B65: F2 | C65: f2-q3 | D65: How did the money income Gini index change between 2021 and 2022? | E65: text | F65: from 0.494 to 0.488 | G65: R1w | H65: 1 | I65: yes | J65: yes | K65: census-p60-279.pdf | L65: Income in the United States: 2022 > HOUSEHOLD INCOME BY SELECTED CHARACTERISTICS > Money Income Inequality27 | M65: Money Income Inequality27 The Gini index is a statistical mea sure of income inequality ranging from 0.0 to 1.0. It measures the amount that any two incomes differ, on average, relative to mean income. It is an indicator of how far apart or “sp
A66: R1w | B66: F2 | C66: f2-q4 | D66: What was the median income of married-couple households in 2022 according to Table A-1? | E66: table | F66: married-couple + 110,800 | G66: R1w | I66: no | J66: no | K66: census-p60-279.pdf | L66: Income in the United States: 2022 > HOUSEHOLD INCOME BY SELECTED CHARACTERISTICS > Type of Household8 | M66: Type of Household8 The 2022 real median income of family households declined by 2.9 percent from 2021, and the real median income of marriedcouple families declined by 3.9 percent. Among family house holds, married couples had the highest media
A67: R1w | B67: F2 | C67: f2-q5 | D67: What was the median income of family households in 2022 according to Table A-1? | E67: table | F67: family households + 95,450 | G67: R1w | I67: no | J67: no | K67: census-p60-279.pdf | L67: Income in the United States: 2022 > HOUSEHOLD INCOME BY SELECTED CHARACTERISTICS > Type of Household8 | M67: Type of Household8 The 2022 real median income of family households declined by 2.9 percent from 2021, and the real median income of marriedcouple families declined by 3.9 percent. Among family house holds, married couples had the highest media
A68: R1w | B68: F2 | C68: f2-q6 | D68: What was the median income of nonfamily households in 2022 according to Table A-1? | E68: table | F68: nonfamily households + 45,440 | G68: R1w | H68: 1 | I68: yes | J68: yes | K68: census-p60-279.pdf | L68: Income in the United States: 2022 > HOUSEHOLD INCOME BY SELECTED CHARACTERISTICS > Type of Household8 | M68: an income between these groups and non-Hispanic White households decreased.12 Nonfamily households had a median income of $45,440 in 2022, which was not significantly different from 2021 (Figure 1 and Table A-1). Nonfamily house holds with a
A69: R1w | B69: F2 | C69: f2-q7 | D69: What was the median household income in Canada in 2022? | E69: unanswerable | F69: (not in source) | G69: R1w | I69: n/a | J69: n/a | K69: census-p60-279.pdf | L69: Income in the United States: 2022 > HOUSEHOLD INCOME BY SELECTED CHARACTERISTICS > All Households | M69: All Households Real median household income was $74,580 in 2022, 2.3 percent lower than the 2021 estimate of $76,330. It was 4.7 percent lower than the 2019 median, the year before the start of the COVID-19 pandemic and the corresponding rece
A70: R1w | B70: F3 | C70: f3-q1 | D70: How many television pictures does Part III of the Surveyor VI report present? | E70: ocr | F70: 139 of the total number | G70: R1w | H70: 1 | I70: yes | J70: yes | K70: surveyor-vi-tv-scan.pdf | M70: ists of selected pictures from Surveyor VI and appropriate explanatory material. This Part III presents 139 of the total number of television pictures transmitted to earth from the lunar surface, between November 10 and November 24, 1967; 46 mosaics
A71: R1w | B71: F3 | C71: f3-q2 | D71: Between which dates were the Surveyor VI television pictures transmitted? | E71: ocr | F71: november 10 and november 24, 1967 | G71: R1w | H71: 1 | I71: yes | J71: yes | K71: surveyor-vi-tv-scan.pdf | M71: ists of selected pictures from Surveyor VI and appropriate explanatory material. This Part III presents 139 of the total number of television pictures transmitted to earth from the lunar surface, between November 10 and November 24, 1967; 46 mosaics
A72: R1w | B72: F3 | C72: f3-q3 | D72: How many mosaics are included in Part III? | E72: ocr | F72: 46 mosaics | G72: R1w | H72: 1 | I72: yes | J72: yes | K72: surveyor-vi-tv-scan.pdf | M72: ists of selected pictures from Surveyor VI and appropriate explanatory material. This Part III presents 139 of the total number of television pictures transmitted to earth from the lunar surface, between November 10 and November 24, 1967; 46 mosaics
A73: R1w | B73: F3 | C73: f3-q4 | D73: What is the mass of the Surveyor survey TV camera? | E73: ocr | F73: 7.3-kg camera | G73: R1w | H73: 3 | I73: no | J73: yes | K73: surveyor-vi-tv-scan.pdf | M73: Il. Television Subsystem M. I. Smokler The Surveyor TV system is designed to obtain video pictures of the lunar surface, lunar sky, and portions of the landed spacecraft. It includes a survey camera capable of panoramic viewing, and a TV auxiliary t
A74: R1w | B74: F3 | C74: f3-q5 | D74: Over what range can the Surveyor TV camera focus? | E74: ocr | F74: 1.22 m to infinity | G74: R1w | H74: 4 | I74: no | J74: yes | K74: surveyor-vi-tv-scan.pdf | M74: was capable of providing either a Fig. II-5. Variable-focal-length lens assembly 100-mm or 25-mm focal length, resulting in a vertical field of view of approximately 6.43 or 25.3 deg, respectively, as measured by the angular subtense of the vertic
A75: R1w | B75: F3 | C75: f3-q6 | D75: What scene luminance range is the Surveyor camera designed to accommodate? | E75: ocr | F75: 0.008 to 2600 ft-l | G75: R1w | H75: 1 | I75: yes | J75: yes | K75: surveyor-vi-tv-scan.pdf | M75: tification signals and to provide appropriate video mixing. A. Camera Description The slow-scan survey TV camera, shown in Figs. II-1 and II-2, provides images of the lunar surface over a 360-deg panorama. Each picture, or frame, is imaged through
A76: R1w | B76: F3 | C76: f3-q7 | D76: Which mission number in the Surveyor series was Surveyor VI? | E76: ocr | F76: the sixth in a series of unmanned lunar soft-landing missions | G76: R1w | H76: 1 | I76: yes | J76: yes | K76: surveyor-vi-tv-scan.pdf | M76: Preface This three-part document constitutes the Project Mission Report on Surveyor VI, the sixth in a series of unmanned lunar soft-landing missions. Part I of this Technical Report consists of a technical description and an evaluation of engineer
A77: R1w | B77: F3 | C77: f3-q8 | D77: What was the landing site latitude of Surveyor VII? | E77: unanswerable | F77: (not in source) | G77: R1w | I77: n/a | J77: n/a | K77: surveyor-vi-tv-scan.pdf | M77: Preface This three-part document constitutes the Project Mission Report on Surveyor VI, the sixth in a series of unmanned lunar soft-landing missions. Part I of this Technical Report consists of a technical description and an evaluation of engineer
A78: R2 | B78: F1 | C78: f1-q1 | D78: What are the layer, hidden size and attention head settings of BERT-base? | E78: text | F78: l=12, h=768, a=12 | G78: R2 | H78: 3 | I78: no | J78: yes | K78: acl-n19-1423-bert.pdf | M78: .99 84.4 86.7 92.9 12 1024 16 3.54 85.7 86.9 93.3 24 1024 16 3.23 86.6 87.8 93.7 Table 6: Ablation over BERT model size. #L = the number of layers; #H = hidden size; #A = number of attention heads. “LM (ppl)” is the masked LM perplexity of held-out
A79: R2 | B79: F1 | C79: f1-q2 | D79: What percentage of WordPiece tokens does BERT mask during pre-training? | E79: text | F79: 15% of all wordpiece | G79: R2 | H79: 3 | I79: no | J79: yes | K79: acl-n19-1423-bert.pdf | M79: The numbers in the left part of the table represent the probabilities of the speciﬁc strategies used during MLM pre-training (BERT uses 80%, 10%, 10%). The right part of the paper represents the Dev set results. For the feature-based approach, we con
A80: R2 | B80: F1 | C80: f1-q3 | D80: What GLUE score did BERT reach? | E80: text | F80: glue score to 80.5% | G80: R2 | H80: 3 | I80: no | J80: yes | K80: acl-n19-1423-bert.pdf | M80: Results are presented in Table 1. Both BERTBASE and BERTLARGE outperform all systems on all tasks by a substantial margin, obtaining 4.5% and 7.0% respective average accuracy improvement over the prior state of the art. Note that BERTBASE and OpenAI
A81: R2 | B81: F1 | C81: f1-q4 | D81: Which corpora were used to pre-train BERT? | E81: text | F81: bookscorpus (800m words) | G81: R2 | H81: 2 | I81: no | J81: yes | K81: acl-n19-1423-bert.pdf | L81: 3.1 Pre-training BERT | M81: 3.1 Pre-training BERT
A82: R2 | B82: F1 | C82: f1-q5 | D82: What SQuAD v1.1 Test F1 did BERT achieve? | E82: text | F82: 93.2 | G82: R2 | H82: 2 | I82: no | J82: yes | K82: acl-n19-1423-bert.pdf | M82: Table 4: SWAG Dev and Test accuracies. †Human performance is measured with 100 samples, as reported in the SWAG paper. ˆ si,j = maxj≥iS·Ti + E·Tj. We predict a non-null answer when ˆ si,j > snull + τ, where the threshold τ is selected on the dev set
A83: R2 | B83: F1 | C83: f1-q6 | D83: How many total parameters does BERT-large have? | E83: text | F83: total parameters=340m | G83: R2 | H83: 1 | I83: yes | J83: yes | K83: acl-n19-1423-bert.pdf | L83: We primarily report results on two model sizes: BERTBASE (L=12, H=768, A=12, Total Parameters=110M) and BERTLARGE (L=24, H=1024, A=16, Total Parameters=340M). | M83: We primarily report results on two model sizes: BERTBASE (L=12, H=768, A=12, Total Parameters=110M) and BERTLARGE (L=24, H=1024, A=16, Total Parameters=340M).
A84: R2 | B84: F1 | C84: f1-q7 | D84: How many GPUs were used to train GPT-4? | E84: unanswerable | F84: (not in source) | G84: R2 | I84: n/a | J84: n/a | K84: acl-n19-1423-bert.pdf | M84: • GPT was trained for 1M steps with a batch size of 32,000 words; BERT was trained for 1M steps with a batch size of 128,000 words. • GPT used the same learning rate of 5e-5 for all ﬁne-tuning experiments; BERT chooses a task-speciﬁc ﬁne-tuning lear
A85: R2 | B85: F2 | C85: f2-q1 | D85: What was real median household income in the United States in 2022? | E85: text | F85: $74,580 | G85: R2 | H85: 1 | I85: yes | J85: yes | K85: census-p60-279.pdf | M85: Real median household income was $74,580 in 2022, 2.3 percent lower than the 2021 estimate of $76,330. It was 4.7 percent lower than the 2019 median, the year before the start of the COVID-19 pandemic and the corresponding recession (Figure 1
A86: R2 | B86: F2 | C86: f2-q2 | D86: By how much did real median household income change between 2021 and 2022? | E86: text | F86: 2.3 percent | G86: R2 | H86: 2 | I86: no | J86: yes | K86: census-p60-279.pdf | L86: Change: 2021 to 2022 2022 Median Income | M86: Change: 2021 to 2022 2022 Median Income
A87: R2 | B87: F2 | C87: f2-q3 | D87: How did the money income Gini index change between 2021 and 2022? | E87: text | F87: from 0.494 to 0.488 | G87: R2 | H87: 1 | I87: yes | J87: yes | K87: census-p60-279.pdf | M87: The Gini index is a statistical mea sure of income inequality ranging from 0.0 to 1.0. It measures the amount that any two incomes differ, on average, relative to mean income. It is an indicator of how far apart or “spread out” incomes are from
A88: R2 | B88: F2 | C88: f2-q4 | D88: What was the median income of married-couple households in 2022 according to Table A-1? | E88: table | F88: married-couple + 110,800 | G88: R2 | I88: no | J88: no | K88: census-p60-279.pdf | M88: The 2022 real median income of family households declined by 2.9 percent from 2021, and the real median income of marriedcouple families declined by 3.9 percent. Among family house holds, married couples had the highest median income in 2022 ($
A89: R2 | B89: F2 | C89: f2-q5 | D89: What was the median income of family households in 2022 according to Table A-1? | E89: table | F89: family households + 95,450 | G89: R2 | I89: no | J89: no | K89: census-p60-279.pdf | M89: The 2022 real median income of family households declined by 2.9 percent from 2021, and the real median income of marriedcouple families declined by 3.9 percent. Among family house holds, married couples had the highest median income in 2022 ($
A90: R2 | B90: F2 | C90: f2-q6 | D90: What was the median income of nonfamily households in 2022 according to Table A-1? | E90: table | F90: nonfamily households + 45,440 | G90: R2 | H90: 1 | I90: yes | J90: yes | K90: census-p60-279.pdf | M90: an income between these groups and non-Hispanic White households decreased.12 Nonfamily households had a median income of $45,440 in 2022, which was not significantly different from 2021 (Figure 1 and Table A-1). Nonfamily house holds with a
A91: R2 | B91: F2 | C91: f2-q7 | D91: What was the median household income in Canada in 2022? | E91: unanswerable | F91: (not in source) | G91: R2 | I91: n/a | J91: n/a | K91: census-p60-279.pdf | M91: Real median household income was $74,580 in 2022, 2.3 percent lower than the 2021 estimate of $76,330. It was 4.7 percent lower than the 2019 median, the year before the start of the COVID-19 pandemic and the corresponding recession (Figure 1
A92: R2 | B92: F3 | C92: f3-q1 | D92: How many television pictures does Part III of the Surveyor VI report present? | E92: ocr | F92: 139 of the total number | G92: R2 | H92: 1 | I92: yes | J92: yes | K92: surveyor-vi-tv-scan.pdf | M92: ists of selected pictures from Surveyor VI and appropriate explanatory material. This Part III presents 139 of the total number of television pictures transmitted to earth from the lunar surface, between November 10 and November 24, 1967; 46 mosai
A93: R2 | B93: F3 | C93: f3-q2 | D93: Between which dates were the Surveyor VI television pictures transmitted? | E93: ocr | F93: november 10 and november 24, 1967 | G93: R2 | H93: 1 | I93: yes | J93: yes | K93: surveyor-vi-tv-scan.pdf | M93: ists of selected pictures from Surveyor VI and appropriate explanatory material. This Part III presents 139 of the total number of television pictures transmitted to earth from the lunar surface, between November 10 and November 24, 1967; 46 mosai
A94: R2 | B94: F3 | C94: f3-q3 | D94: How many mosaics are included in Part III? | E94: ocr | F94: 46 mosaics | G94: R2 | H94: 1 | I94: yes | J94: yes | K94: surveyor-vi-tv-scan.pdf | M94: ists of selected pictures from Surveyor VI and appropriate explanatory material. This Part III presents 139 of the total number of television pictures transmitted to earth from the lunar surface, between November 10 and November 24, 1967; 46 mosai
A95: R2 | B95: F3 | C95: f3-q4 | D95: What is the mass of the Surveyor survey TV camera? | E95: ocr | F95: 7.3-kg camera | G95: R2 | H95: 2 | I95: no | J95: yes | K95: surveyor-vi-tv-scan.pdf | M95: Il. Television Subsystem M. I. Smokler The Surveyor TV system is designed to obtain video camera Z axis to —60 deg below this same plane. The pictures of the lunar surface, lunar sky, and portions of camera Z axis is inclined approximately 16 de
A96: R2 | B96: F3 | C96: f3-q5 | D96: Over what range can the Surveyor TV camera focus? | E96: ocr | F96: 1.22 m to infinity | G96: R2 | H96: 4 | I96: no | J96: yes | K96: surveyor-vi-tv-scan.pdf | M96: s and identification signals generated by sequencing the shutter with appropriate and to provide appropriate video mixing. lens settings and mirror azimuth and elevation position- ing to obtain selected views of the object space. The A. Camera D
A97: R2 | B97: F3 | C97: f3-q6 | D97: What scene luminance range is the Surveyor camera designed to accommodate? | E97: ocr | F97: 0.008 to 2600 ft-l | G97: R2 | I97: no | J97: no | K97: surveyor-vi-tv-scan.pdf | M97: s and identification signals generated by sequencing the shutter with appropriate and to provide appropriate video mixing. lens settings and mirror azimuth and elevation position- ing to obtain selected views of the object space. The A. Camera D
A98: R2 | B98: F3 | C98: f3-q7 | D98: Which mission number in the Surveyor series was Surveyor VI? | E98: ocr | F98: the sixth in a series of unmanned lunar soft-landing missions | G98: R2 | H98: 1 | I98: yes | J98: yes | K98: surveyor-vi-tv-scan.pdf | M98: Preface This three-part document constitutes the Project Mission Report on Surveyor VI, the sixth in a series of unmanned lunar soft-landing missions. Part I of this Technical Report consists of a technical description and an evaluation of engine
A99: R2 | B99: F3 | C99: f3-q8 | D99: What was the landing site latitude of Surveyor VII? | E99: unanswerable | F99: (not in source) | G99: R2 | I99: n/a | J99: n/a | K99: surveyor-vi-tv-scan.pdf | M99: Preface This three-part document constitutes the Project Mission Report on Surveyor VI, the sixth in a series of unmanned lunar soft-landing missions. Part I of this Technical Report consists of a technical description and an evaluation of engine
A100: R3a | B100: F1 | C100: f1-q1 | D100: What are the layer, hidden size and attention head settings of BERT-base? | E100: text | F100: l=12, h=768, a=12 | G100: R3a | H100: 2 | I100: no | J100: yes | K100: acl-n19-1423-bert.pdf | L100: Language Understanding > 5 Ablation Studies > 5.3 Feature-based Approach with BERT | M100: .99 84.4 86.7 92.9 12 1024 16 3.54 85.7 86.9 93.3 24 1024 16 3.23 86.6 87.8 93.7 Table 6: Ablation over BERT model size. #L = the number of layers; #H = hidden size; #A = number of attention heads. “LM (ppl)” is the masked LM perplexity of held-out
A101: R3a | B101: F1 | C101: f1-q2 | D101: What percentage of WordPiece tokens does BERT mask during pre-training? | E101: text | F101: 15% of all wordpiece | G101: R3a | H101: 2 | I101: no | J101: yes | K101: acl-n19-1423-bert.pdf | L101: Language Understanding > 3 BERT > 3.1 Pre-training BERT | M101: ), we only predict the masked words rather than reconstructing the entire input. Although this allows us to obtain a bidirectional pre-trained model, a downside is that we are creating a mismatch between pre-training and ﬁne-tuning, since the [MASK]
A102: R3a | B102: F1 | C102: f1-q3 | D102: What GLUE score did BERT reach? | E102: text | F102: glue score to 80.5% | G102: R3a | H102: 5 | I102: no | J102: yes | K102: acl-n19-1423-bert.pdf | L102: Language Understanding > 4 Experiments > 4.1 GLUE | M102: 85.8 88.9 66.4 79.6 BERTLARGE 86.7/85.9 72.1 92.7 94.9 60.5 86.5 89.3 70.1 82.1 Table 1: GLUE Test results, scored by the evaluation server (https://gluebenchmark.com/leaderboard). The number below each task denotes the number of training examples.
A103: R3a | B103: F1 | C103: f1-q4 | D103: Which corpora were used to pre-train BERT? | E103: text | F103: bookscorpus (800m words) | G103: R3a | H103: 1 | I103: yes | J103: yes | K103: acl-n19-1423-bert.pdf | L103: Language Understanding > 3 BERT > 3.1 Pre-training BERT | M103: ks, where BERT transfers all parameters to initialize end-task model parameters. Pre-training data The pre-training procedure largely follows the existing literature on language model pre-training. For the pre-training corpus we use the BooksCorpus
A104: R3a | B104: F1 | C104: f1-q5 | D104: What SQuAD v1.1 Test F1 did BERT achieve? | E104: text | F104: 93.2 | G104: R3a | H104: 2 | I104: no | J104: yes | K104: acl-n19-1423-bert.pdf | L104: Language Understanding > 4 Experiments > 4.2 SQuAD v1.1 | M104: rst ﬁne-tuning on TriviaQA (Joshi et al., 2017) befor ﬁne-tuning on SQuAD. Our best performing system outperforms the top leaderboard system by +1.5 F1 in ensembling and +1.3 F1 as a single system. In fact, our single BERT model outperforms the top
A105: R3a | B105: F1 | C105: f1-q6 | D105: How many total parameters does BERT-large have? | E105: text | F105: total parameters=340m | G105: R3a | H105: 2 | I105: no | J105: yes | K105: acl-n19-1423-bert.pdf | L105: Language Understanding > 5 Ablation Studies > 5.2 Effect of Model Size | M105: e literature is (L=64, H=512, A=2) with 235M parameters (Al-Rfou et al., 2018). By contrast, BERTBASE contains 110M parameters and BERTLARGE contains 340M parameters. It has long been known that increasing the model size will lead to continual imp
A106: R3a | B106: F1 | C106: f1-q7 | D106: How many GPUs were used to train GPT-4? | E106: unanswerable | F106: (not in source) | G106: R3a | I106: n/a | J106: n/a | K106: acl-n19-1423-bert.pdf | L106: Language Understanding > 5 Ablation Studies > 5.2 Effect of Model Size | M106: Results on selected GLUE tasks are shown in Table 6. In this table, we report the average Dev Set accuracy from 5 random restarts of ﬁne-tuning. We can see that larger models lead to a strict accuracy improvement across all four datasets, even for MR
A107: R3a | B107: F2 | C107: f2-q1 | D107: What was real median household income in the United States in 2022? | E107: text | F107: $74,580 | G107: R3a | H107: 1 | I107: yes | J107: yes | K107: census-p60-279.pdf | L107: Income in the United States: 2022 > HOUSEHOLD INCOME BY SELECTED CHARACTERISTICS > All Households | M107: All Households Real median household income was $74,580 in 2022, 2.3 percent lower than the 2021 estimate of $76,330. It was 4.7 percent lower than the 2019 median, the year before the start of the COVID-19 pandemic and the corresponding rece
A108: R3a | B108: F2 | C108: f2-q2 | D108: By how much did real median household income change between 2021 and 2022? | E108: text | F108: 2.3 percent | G108: R3a | H108: 2 | I108: no | J108: yes | K108: census-p60-279.pdf | L108: Income in the United States: 2022 > HOUSEHOLD INCOME BY SELECTED CHARACTERISTICS > Change: 2021 to 2022 2022 Median Income | M108: Change: 2021 to 2022 2022 Median Income
A109: R3a | B109: F2 | C109: f2-q3 | D109: How did the money income Gini index change between 2021 and 2022? | E109: text | F109: from 0.494 to 0.488 | G109: R3a | H109: 1 | I109: yes | J109: yes | K109: census-p60-279.pdf | L109: Income in the United States: 2022 > HOUSEHOLD INCOME BY SELECTED CHARACTERISTICS > Money Income Inequality27 | M109: Money Income Inequality27 The Gini index is a statistical mea sure of income inequality ranging from 0.0 to 1.0. It measures the amount that any two incomes differ, on average, relative to mean income. It is an indicator of how far apart or “sp
...

Sheet Answers
A1: Round | B1: Index used | C1: Question ID | D1: Question | E1: Reference answer | F1: Model answer | G1: Label (blind) | H1: Reason | I1: Supported by cited evidence | J1: Supported reason | K1: Cost (USD)
A2: R1 | B2: R1 | C2: w1-q1 | D2: Which class does the Python tutorial recommend for implementing a queue? | E2: collections.deque | F2: The Python tutorial recommends using `collections.deque` for implementing a queue because it is designed for fast appends and pops from both ends [S2, S1]. | G2: correct | H2: Names collections.deque. | I2: yes | J2: A cited chunk contains the expected phrase. | K2: 0.0005419
A3: R1 | B3: R1 | C3: w1-q3 | D3: What command does the tutorial use to create a virtual environment called tutorial-env? | E3: python -m venv tutorial-env | F3: The tutorial uses the command `python -m venv tutorial-env` to create a virtual environment named tutorial-env [S1]. | G3: correct | H3: Gives python -m venv tutorial-env. | I3: yes | J3: A cited chunk contains the expected phrase. | K3: 0.0005854
A4: R1 | B4: R1 | C4: w1-q8 | D4: On what date will Python 4.0 be released according to the tutorial? | E4: Not stated in the source. | F4: INSUFFICIENT_EVIDENCE. The provided text does not specify a release date for Python 4.0. In fact, according to Guido van Rossum, Python 4.0 will probably never exist [S3]. | G4: correct-abstain | H4: Declines; adds a cited aside that does not invent a date. | I4: n/a | J4: No answer to support. | K4: 0.0006461
A5: R1 | B5: R1 | C5: w2-q1 | D5: What is the elevation of Mount Everest in metres? | E5: 8,848.86 m (29,031.7 ft) | F5: The elevation of Mount Everest is 8,848.86 meters (29,031.7 ft) [S4]. This new official height was jointly announced by China and Nepal on December 8, 2020 [S2]. | G5: correct | H5: States 8,848.86 m. | I5: yes | J5: A cited chunk contains the expected phrase. | K5: 0.0007964
A6: R1 | B6: R1 | C6: w2-q3 | D6: What is the average discharge of the Amazon River? | E6: About 215,000 to 230,000 cubic meters per second. | F6: The Amazon River has an average discharge of about 215,000 to 230,000 cubic meters per second [S2]. Specifically, the average discharge at the estuary from 2003 to 2015 was 230,000 m³/s [S1]. If the Amazon and Rio Pará are considered a single water system, the total discharge at the Amazon Delta averages 223,700 m³/s, or 230,000 m³/s for the period 2003–2015 [S3]. | G6: correct | H6: States 215,000 to 230,000 m3/s. | I6: yes | J6: A cited chunk contains the expected phrase. | K6: 0.001366
A7: R1 | B7: R1 | C7: w2-q5 | D7: Who published the first generally accepted periodic table, and in what year? | E7: Dmitri Mendeleev, in 1869. | F7: The first generally accepted periodic table was published by the Russian chemist Dmitri Mendeleev in 1869 [S1]. | G7: correct | H7: Mendeleev, 1869. | I7: yes | J7: A cited chunk contains the expected phrase. | K7: 0.0005045
A8: R1 | B8: R1 | C8: w3-q1 | D8: What was the minimum hourly wage for workers under 18 from April 2024 to March 2025? | E8: £6.40 | F8: The minimum hourly wage for workers under 18 from April 2024 to March 2025 was £6.40 [S1]. | G8: correct | H8: States £6.40. | I8: yes | J8: A cited chunk contains the expected phrase. | K8: 0.00014812
A9: R1 | B9: R1 | C9: w3-q2 | D9: Which taxable income band does the 40% higher rate of Income Tax cover? | E9: £50,271 to £125,140 | F9: The 40% higher rate of Income Tax covers taxable income from £50,271 to £125,140 [S1]. | G9: correct | H9: States £50,271 to £125,140. | I9: yes | J9: A cited chunk contains the expected phrase. | K9: 0.0004699
A10: R1 | B10: R1 | C10: w3-q6 | D10: What is the first vehicle tax payment for a petrol car emitting 111 to 130g/km of CO2? | E10: £455 | F10: The first vehicle tax payment for a petrol car emitting 111 to 130g/km of CO2 is £455 [S2]. | G10: correct | H10: States £455 despite the flattened table. | I10: yes | J10: A cited chunk contains the expected phrase. | K10: 0.000811
A11: R1 | B11: R1 | C11: w4-q1 | D11: What does HTTP status 418 I'm a teapot mean? | E11: The server refuses the attempt to brew coffee with a teapot. | F11: The HTTP status 418 I'm a teapot means that the server refuses to brew coffee with a teapot [S1]. | G11: correct | H11: Refuses to brew coffee with a teapot. | I11: yes | J11: A cited chunk contains the expected phrase. | K11: 0.0005778
A12: R1 | B12: R1 | C12: w4-q4 | D12: What is a closure in JavaScript? | E12: The combination of a function bundled together with references to its surrounding state (the lexical environment). | F12: A closure in JavaScript is the combination of a function and its surrounding state (the lexical environment) [S1]. It allows a function to access its outer scope [S1]. Closures are created every time a function is created [S1]. This means that a function maintains access to variables that were in scope when the closure was created, even after the outer function has finished executing [S3, S5]. | G12: correct | H12: Function plus surrounding lexical environment. | I12: yes | J12: A cited chunk contains the expected phrase. | K12: 0.0006591
A13: R1 | B13: R1 | C13: w4-q8 | D13: Which HTTP status code means Payment Accepted? | E13: Not stated in the source (no such status code). | F13: INSUFFICIENT_EVIDENCE. The provided documents do not list an HTTP status code that means "Payment Accepted." They do mention "402 Payment Required," but this is a different meaning [S2]. | G13: correct-abstain | H13: Declines and notes 402 Payment Required is different. | I13: n/a | J13: No answer to support. | K13: 0.0005723
... A118: A3 | B118: A3 | C118: g2-q3 | D118: What does NIST SP 800-63B require for retina scanners at AAL3 in hospitals? | E118: Not stated in the source. | F118: INSUFFICIENT_EVIDENCE. The provided text does not specify requirements for retina scanners, nor does it mention hospitals. It only states general requirements for biometric factors at AAL3 [S1]. | G118: correct-abstain | H118: Declined; not in the source. | I118: n/a | J118: No answer to support. | K118: 0.0004691
A120: Total answer cost (USD) | K120: =SUM(K2:K118)
A121: Labels: correct, correct-abstain, partial, wrong, wrong-abstain. Scored blind by Claude with the spec 0004 rubric; rounds were hidden as X/Y. A1 (after the fixes) and A2 (extractor v4) were scored with the same rubric against the references, not blind.

Sheet Settings verdict
A1: Setting | B1: Where it shows | C1: Default | D1: Tested in | E1: Measured effect | F1: Verdict | G1: Recommendation
A2: If a file can't be read well | B2: Extract panel (visible) | C2: Stop and let me review (Balanced) | D2: R1 vs R1w, R3b, R5 | E2: The default blocked the whole files run in R1 because one ordinary government PDF (Census P60-279) was flagged for malformed tables. 'Publish the other files and show warnings' published it with warnings (R1w), but it does not publish the others when a required file cannot be read at all: R3b (OCR off) still failed the whole run. On websites (R5) it changed nothing because no page failed. | F2: Keep visible | G2: Keep the choice, but fix what it does: 'publish the others' should exclude any unreadable file, not only files marked optional (finding X3). Reconsider the default once X1 and X2 are fixed.
A3: Read scanned pages (OCR) | B3: Extract panel (visible) | C3: On | D3: R3b | E3: Turning it off made the scanned report unreadable and failed the whole files run (and every scan question). Leaving it on costs nothing for text PDFs: OCR ran only on the image-only pages. | F3: Candidate to remove | G3: Always run OCR when the server supports it; show a note only when OCR is unavailable.
A4: Languages in scanned pages | B4: Extract panel (visible when OCR is on) | C4: eng | D4: Not tested | E4: Only English sources and the English language pack were used. | F4: Keep visible | G4: Keep; it matters for non-English scans. Test with a non-English scan before changing it.
A5: Extractor version (v1 / v2) | B5: Upgrade callout only | C5: layout-ocr-v2 | D5: R2 | E5: Retrieval on the three files: Hit@5 16/19 with v1 vs 17/19 with v2 (v1 lost the scan's luminance-range question; both miss the same two Census table questions), Hit@1 8 vs 9. Answers: identical on the 8 file questions (6 correct, 1 correct-abstain, 1 wrong-abstain each). v2 also keeps headings and section paths that v1 does not. | F5: Keep in Advanced | G5: Keep v2 as the default and the upgrade as the only control; no new user setting.
A6: OCR resolution (DPI) | B6: Advanced | C6: 200 | D6: R3a (300) | E6: No change in any retrieval result, structure or answer on the scanned report. | F6: Candidate to remove | G6: Fix at 200 DPI; revisit only if a real low-quality scan shows a difference.
A7: Maximum OCR pages | B7: Advanced | C7: 50 | D7: R3a (100) | E7: No change: the scan had 10 pages. It only matters for scans longer than 50 pages, where the default would fail the file. | F7: Keep in Advanced | G7: Raise the default to the server maximum (100) and keep it in Advanced.
A8: Per-page OCR timeout | B8: Advanced | C8: 30 s | D8: Not changed | E8: No page came close: OCR took about 1-2 s per page. | F8: Candidate to remove | G8: Keep as a fixed server safety limit, not a user setting.
A9: Detect rotation / deskew | B9: Advanced | C9: On | D9: Not changed | E9: The real scan was upright; earlier synthetic tests showed rotation is needed for sideways scans and costs little. | F9: Candidate to remove | G9: Always on.
A10: Extraction strategy (Auto / Native / Layout-aware) | B10: Advanced | C10: Auto | D10: Not changed | E10: Auto handled the two-column paper, the report and the scan; Auto picked layout analysis on every text page. | F10: Candidate to remove | G10: Fix at Auto.
A11: Table evidence (Structured + Markdown / Markdown / Plain text) | B11: Advanced | C11: Structured + Markdown | D11: R4 (plain text) | E11: No change in any retrieval result (Hit@1 24, Hit@5 42 both); 684 vs 718 chunks. It does not apply to websites. | F11: Candidate to remove | G11: Fix at Structured + Markdown.
A12: Quality thresholds (empty pages, characters, OCR confidence, reading order, malformed tables) | B12: Advanced | C12: Balanced preset | D12: Indirectly (R1) | E12: 'Fail on malformed tables' is what blocked the Census report; 'suspicious reading order' only warned on the BERT paper and the report. | F12: Keep in Advanced | G12: Keep for experts; make the malformed-table check warn, not fail, until X2 is fixed.
... A14: Chunk size (target / maximum / overlap) | B14: Chunk stage | C14: 600 / 800 / 80 | D14: R6 (300 / 400 / 40) | E14: The only setting that moved results both ways: Hit@1 26 vs 24 and Hit@5 42 vs 42 overall; MDN improved (Hit@5 6 to 7, Hit@1 4 to 6), the scan improved at rank 1, two Wikipedia questions were gained and two lost, one BERT question was lost. Doubles the chunks and the embedding cost. | F14: Keep visible | G14: Keep 600 / 800 / 80 as the default and keep chunk size visible in the Chunk stage.

Sheet Findings
A1: ID | B1: Severity | C1: Finding | D1: Evidence | E1: Impact on users | F1: Next step | G1: After fixes (spec 0007) | H1: After-fixes evidence
A2: X1 | B2: High | C2: The recommended setting ('Stop and let me review') blocks an ordinary government report. | D2: R1 files run failed: Census P60-279 was flagged malformed_tables (19 tables) under the Balanced policy, so no file index was published. The free preview showed the same before any paid step. | E2: A user who uploads a normal statistical report with the defaults gets no index at all and must change a setting they do not understand. | F2: Fix X2; until then make malformed tables a warning in Balanced. | G2: Fixed | H2: A1 files run with 'Stop and let me review' published all three files; the Census report is no longer blocked (layout-ocr-v3).
A3: X2 | B3: High | C3: Borderless PDF tables lose their rows: whole columns are merged into one cell, and cells over 1,000 characters are cut. | D3: Census Table A-1 (page 21): one cell holds '74,580 95,450 110,800 56,030 ...' with the row names in a different cell; 19 tables were cut at the 1,000-character cell limit. f2-q4 and f2-q5 missed in every round; the answer model declined f2-q4 in both v1 and v2. | E3: Values from report tables cannot be matched to their rows, so table questions on real reports fail or are declined; data past the cut is lost. | F3: New extractor version: detect merged-column tables (cells with many line-separated values) and fall back to text lines for those tables instead of truncating. | G3: Fixed | H3: f2-q4 and f2-q5 now retrieve their Table A-1 row (rank 2 and 4; before: not in the top 5). f2-q4 answer changed from wrongly declined to correct ($110,800). Rotated landscape tables are kept whole but transposed (known limit).
A4: X3 | B4: High | C4: 'Publish the other files and show warnings' does not publish the others when a file cannot be read. | D4: R3b (OCR off) with warn-v1: the scanned report had no text, and the whole files run failed instead of excluding it. warn-v1 only excludes files marked optional. | E4: The plain-language choice in the Extract panel promises more than it does. | F4: Either exclude any unreadable file under this choice, or reword it to match the behaviour. | G4: Fixed (tests) | H4: Covered by PostgreSQL tests for files, S3 and Website runs: an unreadable item is skipped and the rest publish. Not re-run live: no A1 item failed.
A5: X4 | B5: Medium | C5: Website tables are flattened to one value per line. | D5: GOV.UK minimum-wage and vehicle-tax tables and the Wikipedia infobox appear as single values on separate lines; the column a value belongs to is lost. No website chunk is stored as a table. | E5: Answers that depend on a column can go wrong; in this test the model still answered the three website table questions correctly. | F5: Render HTML tables as Markdown rows in the website extractor (new web extractor version). | G5: Fixed | H5: A1 website index has 156 table chunks, all with a header row (R1: 0).
A6: X5 | B6: Medium | C6: Line-break de-hyphenation merges real hyphenated words. | D6: 'married-\ncouple' in the Census report became 'marriedcouple' after Clean. | E6: Search for the hyphenated term and exact quotes can miss. | F6: Keep the hyphen when both parts are dictionary words or the hyphen is followed by a lowercase word that also appears hyphenated elsewhere. | G6: Mostly fixed | H6: 4 of 5 'married-couple' occurrences in the Census report keep their hyphen; one still reads 'marriedcouple' (cause not yet traced).
A7: X6 | B7: Low | C7: On long Wikipedia articles the lead paragraph can rank below notes and references. | D7: w2-q2 (reef count) and w2-q6 (Moon distance) found the right page but not the lead chunk in R1; references and explanatory notes are indexed. | E7: Lower rank for the most important facts on long pages. | F7: Consider excluding reference lists and footnotes from website chunks. | G7: Fixed | H7: No chunk from a References/Notes/External links section and no 'Retrieved ...' citation text in the A1 website index.
A8: X7 | B8: Low | C8: Website run details list out-of-scope links as succeeded with 0 chunks, often twice. | D8: The Python crawl reports 56 items, including changelog, genindex and licence pages outside /3/tutorial/; only the 17 tutorial pages were indexed. | E8: Run details look as if unwanted pages were ingested. | F8: Show discovered-but-out-of-scope links as excluded with a reason, once each. | G8: Fixed (tests) | H8: PostgreSQL test: an out-of-scope link found twice is listed once as excluded/skipped. A1 reused the R1 snapshot, so no new crawl links were listed.
A9: X8 | B9: Low | C9: Embedding cost is not recorded by the app. | D9: Ingestion runs and indexes have no cost field; this test used an upper-bound estimate from indexed bytes. | E9: Indexing cost shows as unknown in the product. | F9: Record provider-reported embedding tokens and cost per run. | G9: Fixed | H9: The app recorded provider-reported embedding usage: websites 137,559 tokens / $0.0028; files 0 tokens / $0 (every vector reused).
A10: X9 | B10: Medium | C10: A combined citation such as [S1, S2] is recorded as invalid, so the answer shows no valid citation. | D10: A1: w1-q1, f2-q4, f2-q6, f3-q1 cite '[S1, S2]'-style groups and have valid=[]; R1 shows the same (w1-q1, w4-q4). validate_citations() treats the whole bracket as one label. | E10: Correct, supported answers look uncited in the evidence view. | F10: Split a bracket on commas before checking labels; add a test. | G10: Fixed | H10: Found during the spec 0007 re-run. validate_citations() now splits [S1, S2] into S1 and S2, and the answer view links each valid source. Covered by tests; recorded A1 answers keep the citations stored at the time.

Sheet After fixes
A1: Before vs after the spec 0007 fixes (same website snapshot, files and questions)
A2: Before: websites R1, files R1w (R1 files was blocked). After: A1 = extractor v3, files 'Stop and let me review', websites 'Publish the others'.
A4: Track | B4: Measure | C4: Before | D4: After | E4: Note
A5: web | B5: Hit@1 | C5: 15/28 | D5: 18/28
A6: web | B6: Hit@5 | C6: 25/28 | D6: 27/28
A7: web | B7: Recommended run published | C7: succeeded | D7: succeeded
A8: web | B8: Embedding (app-reported) | C8: not recorded | D8: 137559 tokens, $0.00275118 | E8: Reused vectors add nothing
A9: files | B9: Hit@1 | C9: 9/19 | D9: 9/19
A10: files | B10: Hit@5 | C10: 17/19 | D10: 19/19
A11: files | B11: Recommended run published | C11: failed | D11: succeeded | E11: R1 files was blocked by the Census report
A12: files | B12: Embedding (app-reported) | C12: not recorded | D12: 0 tokens, $0.0 | E12: Reused vectors add nothing
A13: both | B13: Answers correct or correctly declined | C13: 19/20 | D13: 20/20 | E13: A1 scored against the references, not blind (one new round)
A15: Questions whose retrieval changed
A16: Question | B16: Source | C16: Question text | D16: First hit rank before | E16: First hit rank after
A17: w2-q2 | B17: W2 | C17: How many individual reefs make up the Great Barrier Reef? | D17: not in top 5 | E17: 1
A18: w2-q6 | B18: W2 | C18: What is the Moon's average distance from Earth? | D18: not in top 5 | E18: 3
A19: w2-q7 | B19: W2 | C19: When was Python 3.0 released? | D19: 2 | E19: 1
A20: w3-q6 | B20: W3 | C20: What is the first vehicle tax payment for a petrol car emitting 111 to 130g/km of CO2? | D20: 2 | E20: 1
A21: f2-q4 | B21: F2 | C21: What was the median income of married-couple households in 2022 according to Table A-1? | D21: not in top 5 | E21: 2
A22: f2-q5 | B22: F2 | C22: What was the median income of family households in 2022 according to Table A-1? | D22: not in top 5 | E22: 4
A24: Findings status
A25: ID | B25: Finding | C25: After fixes | D25: Evidence
A26: X1 | B26: The recommended setting ('Stop and let me review') blocks an ordinary government report. | C26: Fixed | D26: A1 files run with 'Stop and let me review' published all three files; the Census report is no longer blocked (layout-ocr-v3).
A27: X2 | B27: Borderless PDF tables lose their rows: whole columns are merged into one cell, and cells over 1,000 characters are cut. | C27: Fixed | D27: f2-q4 and f2-q5 now retrieve their Table A-1 row (rank 2 and 4; before: not in the top 5). f2-q4 answer changed from wrongly declined to correct ($110,800). Rotated landscape tables are kept whole but transposed (known limit).
A28: X3 | B28: 'Publish the other files and show warnings' does not publish the others when a file cannot be read. | C28: Fixed (tests) | D28: Covered by PostgreSQL tests for files, S3 and Website runs: an unreadable item is skipped and the rest publish. Not re-run live: no A1 item failed.
A29: X4 | B29: Website tables are flattened to one value per line. | C29: Fixed | D29: A1 website index has 156 table chunks, all with a header row (R1: 0).
A30: X5 | B30: Line-break de-hyphenation merges real hyphenated words. | C30: Mostly fixed | D30: 4 of 5 'married-couple' occurrences in the Census report keep their hyphen; one still reads 'marriedcouple' (cause not yet traced).
A31: X6 | B31: On long Wikipedia articles the lead paragraph can rank below notes and references. | C31: Fixed | D31: No chunk from a References/Notes/External links section and no 'Retrieved ...' citation text in the A1 website index.
A32: X7 | B32: Website run details list out-of-scope links as succeeded with 0 chunks, often twice. | C32: Fixed (tests) | D32: PostgreSQL test: an out-of-scope link found twice is listed once as excluded/skipped. A1 reused the R1 snapshot, so no new crawl links were listed.
A33: X8 | B33: Embedding cost is not recorded by the app. | C33: Fixed | D33: The app recorded provider-reported embedding usage: websites 137,559 tokens / $0.0028; files 0 tokens / $0 (every vector reused).
A34: X9 | B34: A combined citation such as [S1, S2] is recorded as invalid, so the answer shows no valid citation. | C34: Fixed | D34: Found during the spec 0007 re-run. validate_citations() now splits [S1, S2] into S1 and S2, and the answer view links each valid source. Covered by tests; recorded A1 answers keep the citations stored at the time.
A36: Note | B36: First A1 website run used html-main-v3, which dropped Python-docs links marked class reference and split sentences at citation markers. Re-run with html-main-v3.1. Its retrieval: hit@5 lost w1-q1, w1-q5, w2-q3, w2-q7 versus R1.

Sheet Extract v4
A1: Extractor v4 against v3 on real files (spec 0008, round A2)
A2: Before: A1 = extractor v3, Maximum OCR pages 50. After: A2 = extractor v4, Maximum OCR pages 100, other Extract settings at the recommended values. The spec 0006 files use 'Stop and let me review'; the new files (F4-F7) use 'Publish the other files and show warnings'. Websites reuse the A1 index: v4 does not change the website reader.
A4: Measure | B4: A1 (v3) | C4: A2 (v4) | D4: Note
A5: Hit@1, spec 0006 file questions | B5: 9/19 | C5: 10/19
A6: Hit@5, spec 0006 file questions | B6: 19/19 | C6: 19/19
A7: File questions found in A1 and missed in A2 | C7: 0 | D7: none
A8: files run | B8: succeeded | C8: succeeded | D8: 637 chunks; embedding 57835 tokens, $0.0011567 (app-reported)
A9: new run | B9: not run | C9: succeeded | D9: 1030 chunks; embedding 94681 tokens, $0.00189362 (app-reported)
A10: Answers correct or correctly declined, spec 0006 file questions | B10: 8/8 | C10: 8/8
A11: File answers correct in A1 and not in A2 | C11: 0 | D11: none
A12: Answers correct or correctly declined, new questions | C12: 11/17
A14: New questions (written from the source files)
A15: Question | B15: Source | C15: Kind | D15: Question text | E15: Reference answer | F15: First hit rank (A2) | G15: Answer label (A2) | H15: Reason
A16: f2-q9 | B16: F2 | C16: table | D16: According to Table A-2, what was the median household income for all races in 2015, in 2022 dollars? | E16: $68,410 | F16: not in top 5 | G16: wrong-abstain | H16: Declined; the Table A-2 2015 row is in the index (correct, read row by row) but not in the top 5, which held the 2019-2022 rows.
A17: f2-q10 | B17: F2 | C17: table | D17: According to Table A-2, what was the mean household income for all races in 1990, in 2022 dollars? | E17: $76,820 | F17: not in top 5 | G17: wrong-abstain | H17: Declined; the 1990 row is in the index but not in the top 5.
A18: f4-q1 | B18: F4 | C18: text | D18: Combien de décès dus aux maladies de l'appareil circulatoire pour 100 000 habitants l'UE-28 comptait-elle en 2015 ? | E18: 381 décès pour 100 000 habitants | F18: not in top 5 | G18: wrong-abstain | H18: Declined; the chart callout '381 deces' is not in the index (chart read as an empty table).
A19: f4-q2 | B19: F4 | C19: text | D19: En 2015, combien de fois plus de risques de mourir d'une maladie de l'appareil circulatoire avait une personne vivant en Bulgarie qu'une personne vivant en France ? | E19: 5,5 fois plus | F19: 1 | G19: correct | H19: 5,5 fois, as the reference.
A20: f4-q3 | B20: F4 | C20: text | D20: Quelle part des marchandises transportées dans l'UE-28 l'est par la route ? | E20: 77 % | F20: 1 | G20: correct | H20: 77 %, as the reference.
A21: f4-q4 | B21: F4 | C21: text | D21: De combien les émissions de gaz à effet de serre de l'UE-28 ont-elles baissé par rapport à 1990 ? | E21: De 22 % par rapport à 1990 | F21: not in top 5 | G21: correct | H21: 22,4 % against 1990 (the prose figure; the chart callout rounds it to 22 %).
A22: f5-q1 | B22: F5 | C22: ocr | D22: Who prepared the compilation of the 1950 water-use estimates in USGS Circular 115? | E22: Kenneth A. MacKichan | F22: 1 | G22: correct | H22: Matches the reference answer.
A23: f5-q2 | B23: F5 | C23: ocr | D23: According to Table 1 of USGS Circular 115, how much surface water did municipalities in Illinois use in 1950 (mgd)? | E23: 1,070 mgd | F23: not in top 5 | G23: wrong-abstain | H23: Declined; the OCR row 'Illinois ... 1,070' is in the index but not in the top 5.
A24: f5-q3 | B24: F5 | C24: ocr | D24: According to Table 1 of USGS Circular 115, how much ground water did municipalities in Kansas use in 1950 (mgd)? | E24: 75 mgd | F24: 2 | G24: wrong-abstain | H24: Declined; the Kansas row is not in the top 5, and OCR reads its 75 as 78.
A25: f6-q1 | B25: F6 | C25: text | D25: What is the word limit for section A3.2, on tackling potholes, in the DfT highways maintenance transparency report template? | E25: 250 words | F25: not in top 5 | G25: wrong-abstain | H25: Declined; the rank-1 chunk has 'Word limit - 250 words' but the A3.2 heading is in an earlier chunk, so the model could not tie the limit to A3.2.
A26: f6-q2 | B26: F6 | C26: table | D26: Into which asset categories does table A4.1 of the DfT template break down spending on highways maintenance? | E26: Carriageways, footways, structures, drainage, street lighting and other assets | F26: 1 | G26: correct | H26: All six categories.
A27: f7-q1 | B27: F7 | C27: table | D27: In the Prevent risk assessment example matrix, what score range counts as medium risk? | E27: 7 to 11 | F27: 1 | G27: correct | H27: 7 to 11, from the slide table.
A28: f7-q2 | B28: F7 | C28: table | D28: In the Prevent risk assessment matrix, which severity of impact has the same rating as a 'Very likely' probability? | E28: Major (rating 4) | F28: 1 | G28: correct | H28: Major, rating 4, from the slide table.
A29: f7-q3 | B29: F7 | C29: table | D29: According to the Prevent slides, on what scale are the severity and likelihood of risks usually ranked? | E29: A 1-5 scale | F29: 3 | G29: correct | H29: 1-5 scale, from the slide table.
A30: f7-q4 | B30: F7 | C30: unanswerable | D30: What score marks a critical risk in the Prevent risk assessment matrix? | E30: Not stated in the source (the highest band is High risk, 12+). | F30: n/a | G30: correct-abstain | H30: Declined; the matrix has no critical band.
A31: f5-q4 | B31: F5 | C31: unanswerable | D31: How much water did Alaska withdraw for irrigation in 1950 according to USGS Circular 115? | E31: Not stated in the source. | F31: n/a | G31: correct-abstain | H31: Declined; Alaska is not in Table 1.
A32: f4-q5 | B32: F4 | C32: unanswerable | D32: Quel était le taux de chômage au Japon en 2018 selon ce rapport ? | E32: Not stated in the source. | F32: n/a | G32: correct-abstain | H32: Declined; not in the report.
A34: Questions whose retrieval changed from A1 to A2
A35: Question | B35: Source | C35: Question text | D35: First hit rank A1 | E35: First hit rank A2
A36: f2-q4 | B36: F2 | C36: What was the median income of married-couple households in 2022 according to Table A-1? | D36: 2 | E36: 1

Sheet Extract v5
A1: Extractor v5 against v4 on real files (spec 0009, round A3)
A2: Before: A2 = extractor v4; the spec 0008 files used 'Publish the other files'. After: A3 = extractor v5 with the same settings, the spec 0008 files under 'Stop and let me review'. The spec 0009 files (G1-G8) use 'Publish the other files and show warnings' so each file's outcome shows. Websites reuse the A1 index.
A4: Measure | B4: A2 (v4) | C4: A3 (v5) | D4: Note
A5: Hit@1, spec 0006 and 0008 file questions | B5: 16/33 | C5: 16/33
A6: Hit@5, spec 0006 and 0008 file questions | B6: 27/33 | C6: 27/33
A7: Found in A2 and missed in A3 | C7: 0 | D7: none
A8: files run | B8: succeeded | C8: succeeded | D8: 707 chunks; embedding 87675 tokens, $0.0017535 (app-reported)
A9: new run | B9: succeeded | C9: succeeded | D9: 1025 chunks; embedding 7873 tokens, $0.00015746 (app-reported)
A10: d2 run | B10: not run | C10: succeeded | D10: 844 chunks; embedding 110195 tokens, $0.0022039 (app-reported)
A11: Answers correct or correctly declined, spec 0006 and 0008 file questions | B11: 19/25 | C11: 19/25
A12: File answers correct in A2 and not in A3 | C12: 0 | D12: none
A13: File answers correct in A3 and not in A2 | C13: 0 | D13: none
A14: Answers correct or correctly declined, spec 0009 questions | C14: 18/19
A16: Spec 0009 files (track d2)
A17: Source | B17: File | C17: Item status | D17: Outcome or reason | E17: Chunks
A18: G1 | B18: IRS Form W-4 (2026), Employee's Withholding Certificate (form with worksheets and tables) | C18: succeeded | E18: 57
A19: G2 | B19: NIST SP 800-63B, Digital Identity Guidelines: Authentication and Lifecycle Management (2017, updated 2020; withdrawn 2025 and kept for history) | C19: succeeded | E19: 466
A20: G3 | B20: GAO-23-900494, Fiscal Year 2024 Budget Request (testimony with charts and tables) | C20: succeeded | E20: 94
A21: G4 | B21: Executive Order 9066 (1942), first page, typed scan, image-only copy | C21: succeeded | E21: 3
A22: G5 | B22: NISRA, Labour Force Survey quarterly tables, October to December 2023 (XLSX, 27 sheets) | C22: succeeded | E22: 94
A23: G6 | B23: ECGD, organisation chart and pay data, September 2012 (PPTX, 3 slides) | C23: succeeded | E23: 8
A24: G7 | B24: DfE, Information sharing agreement template for childminder agencies and local authorities (DOCX) | C24: succeeded | E24: 22
A25: G8 | B25: Pan et al. (2023), Sex difference in driving speed management, PLOS ONE 18(7): e0288653 | C25: succeeded | E25: 100
A27: Spec 0009 questions (written from the source files before the run)
A28: Question | B28: Source | C28: Kind | D28: Question text | E28: Reference answer | F28: First hit rank (A3) | G28: Answer label (A3) | H28: Reason
A29: g1-q1 | B29: G1 | C29: text | D29: On the 2026 Form W-4 Deductions Worksheet, what is the most qualified overtime compensation a filer can enter (not married filing jointly)? | E29: $12,500 ($25,000 if married filing jointly) | F29: 1 | G29: correct | H29: $12,500 with the income condition.
A30: g1-q2 | B30: G1 | C30: text | D30: What standard deduction amount does the 2026 Form W-4 Deductions Worksheet list for head of household? | E30: $24,150 | F30: 1 | G30: correct | H30: Matches the reference answer.
A31: g2-q1 | B31: G2 | C31: text | D31: What minimum length does NIST SP 800-63B set for memorized secrets chosen by the subscriber? | E31: At least 8 characters | F31: 1 | G31: correct | H31: Matches the reference answer.
A32: g2-q2 | B32: G2 | C32: text | D32: Under NIST SP 800-63B, up to what length should verifiers permit subscriber-chosen memorized secrets? | E32: At least 64 characters | F32: 1 | G32: correct | H32: Matches the reference answer.
A33: g3-q1 | B33: G3 | C33: text | D33: According to GAO's fiscal year 2024 budget testimony, how much in financial benefits did GAO's work yield in fiscal year 2022? | E33: $55.6 billion (about $74 for every dollar invested) | F33: 1 | G33: correct | H33: $55.6 billion, as the reference.
A34: g3-q2 | B34: G3 | C34: table | D34: How many GAO mandates did the James M. Inhofe National Defense Authorization Act for Fiscal Year 2023 contain, according to GAO-23-900494? | E34: 158 mandates (312 estimated FTE) | F34: not in top 5 | G34: wrong-abstain | H34: Declined; the mandates table on the Highlights page is split so the Inhofe row and its count are not in one retrieved chunk.
A35: g4-q1 | B35: G4 | C35: ocr | D35: Under Executive Order 9066, whom does the President authorize to prescribe military areas? | E35: The Secretary of War, and the Military Commanders he designates | F35: 3 | G35: correct | H35: The Secretary of War and designated Military Commanders.
A36: g4-q2 | B36: G4 | C36: ocr | D36: Which earlier act, by date, does Executive Order 9066 cite first as defining national-defense material, premises and utilities? | E36: Section 4 of the Act of April 20, 1918 (40 Stat. 533), as amended | F36: 1 | G36: correct | H36: Act of April 20, 1918, 40 Stat. 533.
A37: g5-q1 | B37: G5 | C37: table | D37: According to the NISRA Labour Force Survey tables for October to December 2023, what percentage of females working part time did not want a full-time job? | E37: 73.3% | F37: 1 | G37: correct | H37: 73.3%, from the spreadsheet table.
A38: g5-q2 | B38: G5 | C38: table | D38: What was the economic inactivity rate for all persons aged 16 to 64 in October to December 2023 in the NISRA Labour Force Survey tables? | E38: 26.9% | F38: 3 | G38: correct | H38: 26.9%, from the spreadsheet table.
A39: g6-q1 | B39: G6 | C39: text | D39: Who was the Chief Executive of ECGD in its September 2012 organisation chart? | E39: Patrick Crawford | F39: 4 | G39: correct | H39: Patrick Crawford, from the slide.
A40: g6-q2 | B40: G6 | C40: table | D40: What was the pay range for ECGD Pay Band 07 (SEO) in September 2012? | E40: £36,300 to £43,690 | F40: 1 | G40: correct | H40: £36,300 to £43,690, from the slide.
A41: g7-q1 | B41: G7 | C41: text | D41: In the DfE information sharing agreement template, covering how many years before the application must childminder agencies check where a provider has lived? | E41: The 5 years before the application | F41: 1 | G41: correct | H41: The 5 years before the application.
A42: g7-q2 | B42: G7 | C42: text | D42: Which data protection laws does the childminder information sharing agreement template say agencies and local authorities must understand? | E42: UK GDPR, the Data Protection Act 2018 and, where applicable, the Freedom of Information Act 2000 | F42: 1 | G42: correct | H42: UK GDPR, DPA 2018 and FOI Act 2000.
A43: g8-q1 | B43: G8 | C43: text | D43: How many participants took part in the driving simulator study (study 1) of the PLOS ONE paper on sex differences in driving speed? | E43: 41 | F43: not in top 5 | G43: correct | H43: Forty-one participants.
A44: g8-q2 | B44: G8 | C44: text | D44: In the PLOS ONE driving-speed paper, what partly mediates the relationship between sex and driving speed? | E44: Impulse control (a partial mediating role) | F44: not in top 5 | G44: correct | H44: Impulse control partly mediates the relationship.
A45: g6-q3 | B45: G6 | C45: unanswerable | D45: What was the ECGD Chief Executive's salary in 2015? | E45: Not stated in the source (the chart is as at 30 September 2012). | F45: n/a | G45: correct-abstain | H45: Declined; only 2012 is in the source.
A46: g8-q3 | B46: G8 | C46: unanswerable | D46: How many participants in the PLOS ONE driving-speed study lived in Beijing? | E46: Not stated in the source. | F46: n/a | G46: correct-abstain | H46: Declined; not in the source.
A47: g2-q3 | B47: G2 | C47: unanswerable | D47: What does NIST SP 800-63B require for retina scanners at AAL3 in hospitals? | E47: Not stated in the source. | F47: n/a | G47: correct-abstain | H47: Declined; not in the source.
A49: Questions whose retrieval changed from A2 to A3
A50: Question | B50: Source | C50: Question text | D50: First hit rank A2 | E50: First hit rank A3
A51: f2-q5 | B51: F2 | C51: What was the median income of family households in 2022 according to Table A-1? | D51: 4 | E51: 1
A52: f4-q3 | B52: F4 | C52: Quelle part des marchandises transportées dans l'UE-28 l'est par la route ? | D52: 1 | E52: 2
